[
	{
		"id": 1,
		"fname": "Bud",
		"lname": "Klimek",
		"email": "bklimek0@cyberchimps.com",
		"gender": "Male",
		"phone": "728-806-3167",
		"dob": "8/28/1995"
	},
	{
		"id": 2,
		"fname": "Ailee",
		"lname": "Morgan",
		"email": "amorgan1@uol.com.br",
		"gender": "Non-binary",
		"phone": "420-491-9185",
		"dob": "7/7/2004"
	},
	{
		"id": 3,
		"fname": "Merrie",
		"lname": "Tolan",
		"email": "mtolan2@shutterfly.com",
		"gender": "Polygender",
		"phone": "665-489-6009",
		"dob": "12/15/2005"
	},
	{
		"id": 4,
		"fname": "Alaster",
		"lname": "Babon",
		"email": "ababon3@chronoengine.com",
		"gender": "Genderfluid",
		"phone": "974-210-6379",
		"dob": "1/12/1976"
	},
	{
		"id": 5,
		"fname": "Thaddeus",
		"lname": "MacGibbon",
		"email": "tmacgibbon4@theguardian.com",
		"gender": "Female",
		"phone": "409-913-6047",
		"dob": "3/24/2007"
	},
	{
		"id": 6,
		"fname": "Gavra",
		"lname": "Goscomb",
		"email": "ggoscomb5@networksolutions.com",
		"gender": "Genderqueer",
		"phone": "914-259-7812",
		"dob": "10/15/2003"
	},
	{
		"id": 7,
		"fname": "Ibbie",
		"lname": "Maric",
		"email": "imaric6@oracle.com",
		"gender": "Genderfluid",
		"phone": "879-540-8173",
		"dob": "6/29/1999"
	},
	{
		"id": 8,
		"fname": "Maurie",
		"lname": "Matiewe",
		"email": "mmatiewe7@ihg.com",
		"gender": "Genderqueer",
		"phone": "546-364-0268",
		"dob": "4/19/1994"
	},
	{
		"id": 9,
		"fname": "Othelia",
		"lname": "Stoddart",
		"email": "ostoddart8@tripod.com",
		"gender": "Genderfluid",
		"phone": "454-938-9403",
		"dob": "4/11/2002"
	},
	{
		"id": 10,
		"fname": "Dunc",
		"lname": "Churm",
		"email": "dchurm9@merriam-webster.com",
		"gender": "Genderqueer",
		"phone": "177-134-7670",
		"dob": "12/14/1990"
	},
	{
		"id": 11,
		"fname": "Gaile",
		"lname": "Walkington",
		"email": "gwalkingtona@1und1.de",
		"gender": "Genderqueer",
		"phone": "562-438-2111",
		"dob": "3/24/1974"
	},
	{
		"id": 12,
		"fname": "Ariana",
		"lname": "Critchley",
		"email": "acritchleyb@furl.net",
		"gender": "Bigender",
		"phone": "463-729-6859",
		"dob": "12/7/2009"
	},
	{
		"id": 13,
		"fname": "Brandise",
		"lname": "Nerval",
		"email": "bnervalc@free.fr",
		"gender": "Non-binary",
		"phone": "400-384-8314",
		"dob": "5/13/1986"
	},
	{
		"id": 14,
		"fname": "Jameson",
		"lname": "Gillanders",
		"email": "jgillandersd@businessinsider.com",
		"gender": "Female",
		"phone": "864-623-5501",
		"dob": "5/13/1989"
	},
	{
		"id": 15,
		"fname": "Cointon",
		"lname": "McCloud",
		"email": "cmccloude@discuz.net",
		"gender": "Non-binary",
		"phone": "584-950-4542",
		"dob": "3/12/2003"
	},
	{
		"id": 16,
		"fname": "Katleen",
		"lname": "Corragan",
		"email": "kcorraganf@msu.edu",
		"gender": "Genderqueer",
		"phone": "648-538-7758",
		"dob": "8/6/2006"
	},
	{
		"id": 17,
		"fname": "Ruthanne",
		"lname": "Spearett",
		"email": "rspearettg@feedburner.com",
		"gender": "Female",
		"phone": "117-926-0297",
		"dob": "8/17/1983"
	},
	{
		"id": 18,
		"fname": "Fara",
		"lname": "Heady",
		"email": "fheadyh@comcast.net",
		"gender": "Female",
		"phone": "948-497-0267",
		"dob": "10/28/1998"
	},
	{
		"id": 19,
		"fname": "Dosi",
		"lname": "Yarr",
		"email": "dyarri@xrea.com",
		"gender": "Genderqueer",
		"phone": "274-470-1820",
		"dob": "8/5/1993"
	},
	{
		"id": 20,
		"fname": "Joya",
		"lname": "Hefford",
		"email": "jheffordj@free.fr",
		"gender": "Genderqueer",
		"phone": "889-955-7141",
		"dob": "3/13/2006"
	},
	{
		"id": 21,
		"fname": "Frederique",
		"lname": "Booty",
		"email": "fbootyk@ucoz.ru",
		"gender": "Male",
		"phone": "515-409-7917",
		"dob": "4/18/1976"
	},
	{
		"id": 22,
		"fname": "Alwyn",
		"lname": "Mowne",
		"email": "amownel@creativecommons.org",
		"gender": "Bigender",
		"phone": "363-579-9413",
		"dob": "1/7/1999"
	},
	{
		"id": 23,
		"fname": "Rozanna",
		"lname": "Bateman",
		"email": "rbatemanm@imdb.com",
		"gender": "Non-binary",
		"phone": "394-433-7555",
		"dob": "4/16/1987"
	},
	{
		"id": 24,
		"fname": "Glynn",
		"lname": "Hards",
		"email": "ghardsn@liveinternet.ru",
		"gender": "Genderqueer",
		"phone": "418-364-5448",
		"dob": "8/12/1973"
	},
	{
		"id": 25,
		"fname": "Jammie",
		"lname": "Fergie",
		"email": "jfergieo@reuters.com",
		"gender": "Agender",
		"phone": "313-477-8806",
		"dob": "12/15/1973"
	},
	{
		"id": 26,
		"fname": "Gusty",
		"lname": "Ferreiro",
		"email": "gferreirop@wsj.com",
		"gender": "Female",
		"phone": "767-173-9948",
		"dob": "8/19/1997"
	},
	{
		"id": 27,
		"fname": "Prudy",
		"lname": "McNea",
		"email": "pmcneaq@ask.com",
		"gender": "Agender",
		"phone": "282-787-7999",
		"dob": "10/5/1978"
	},
	{
		"id": 28,
		"fname": "Freeland",
		"lname": "Melanaphy",
		"email": "fmelanaphyr@nba.com",
		"gender": "Bigender",
		"phone": "138-965-5539",
		"dob": "8/1/1996"
	},
	{
		"id": 29,
		"fname": "Jaimie",
		"lname": "Gresham",
		"email": "jgreshams@aboutads.info",
		"gender": "Female",
		"phone": "315-769-2581",
		"dob": "1/29/2003"
	},
	{
		"id": 30,
		"fname": "Bear",
		"lname": "Cottle",
		"email": "bcottlet@biblegateway.com",
		"gender": "Bigender",
		"phone": "222-113-1149",
		"dob": "6/25/1977"
	},
	{
		"id": 31,
		"fname": "Mariele",
		"lname": "Coppock.",
		"email": "mcoppocku@aol.com",
		"gender": "Agender",
		"phone": "138-940-8884",
		"dob": "7/9/2008"
	},
	{
		"id": 32,
		"fname": "Ryon",
		"lname": "Mighele",
		"email": "rmighelev@delicious.com",
		"gender": "Polygender",
		"phone": "982-531-4355",
		"dob": "3/3/1974"
	},
	{
		"id": 33,
		"fname": "Leela",
		"lname": "Briskey",
		"email": "lbriskeyw@baidu.com",
		"gender": "Agender",
		"phone": "829-696-0589",
		"dob": "9/28/1972"
	},
	{
		"id": 34,
		"fname": "Ado",
		"lname": "Golda",
		"email": "agoldax@abc.net.au",
		"gender": "Genderqueer",
		"phone": "743-229-1655",
		"dob": "2/10/2001"
	},
	{
		"id": 35,
		"fname": "Lillis",
		"lname": "Hicklingbottom",
		"email": "lhicklingbottomy@wikispaces.com",
		"gender": "Female",
		"phone": "109-433-1249",
		"dob": "4/28/1985"
	},
	{
		"id": 36,
		"fname": "Riobard",
		"lname": "Coskerry",
		"email": "rcoskerryz@ameblo.jp",
		"gender": "Female",
		"phone": "794-571-6784",
		"dob": "6/25/1985"
	},
	{
		"id": 37,
		"fname": "Nester",
		"lname": "Bleyman",
		"email": "nbleyman10@mit.edu",
		"gender": "Non-binary",
		"phone": "845-414-7025",
		"dob": "8/29/1994"
	},
	{
		"id": 38,
		"fname": "Jori",
		"lname": "Capeling",
		"email": "jcapeling11@wiley.com",
		"gender": "Genderqueer",
		"phone": "956-905-8362",
		"dob": "8/1/2005"
	},
	{
		"id": 39,
		"fname": "Sax",
		"lname": "Pettis",
		"email": "spettis12@ehow.com",
		"gender": "Genderqueer",
		"phone": "607-251-2171",
		"dob": "12/24/1973"
	},
	{
		"id": 40,
		"fname": "August",
		"lname": "Gosnell",
		"email": "agosnell13@yellowpages.com",
		"gender": "Non-binary",
		"phone": "954-598-5798",
		"dob": "6/26/2000"
	},
	{
		"id": 41,
		"fname": "Godfry",
		"lname": "Labb",
		"email": "glabb14@google.de",
		"gender": "Agender",
		"phone": "120-119-3877",
		"dob": "1/11/1996"
	},
	{
		"id": 42,
		"fname": "Stormy",
		"lname": "Fyfield",
		"email": "sfyfield15@multiply.com",
		"gender": "Agender",
		"phone": "996-548-0468",
		"dob": "11/15/1976"
	},
	{
		"id": 43,
		"fname": "Kalina",
		"lname": "Smalls",
		"email": "ksmalls16@bbc.co.uk",
		"gender": "Male",
		"phone": "834-879-1209",
		"dob": "10/26/1979"
	},
	{
		"id": 44,
		"fname": "Arlee",
		"lname": "Blonfield",
		"email": "ablonfield17@hhs.gov",
		"gender": "Female",
		"phone": "609-498-0166",
		"dob": "11/21/1981"
	},
	{
		"id": 45,
		"fname": "Matteo",
		"lname": "Chuney",
		"email": "mchuney18@businessweek.com",
		"gender": "Agender",
		"phone": "347-900-0617",
		"dob": "9/27/1985"
	},
	{
		"id": 46,
		"fname": "Inger",
		"lname": "Paradise",
		"email": "iparadise19@netscape.com",
		"gender": "Bigender",
		"phone": "607-488-8511",
		"dob": "2/25/2001"
	},
	{
		"id": 47,
		"fname": "Kym",
		"lname": "Olenov",
		"email": "kolenov1a@salon.com",
		"gender": "Genderfluid",
		"phone": "846-440-5708",
		"dob": "3/3/1983"
	},
	{
		"id": 48,
		"fname": "Fifine",
		"lname": "Menilove",
		"email": "fmenilove1b@51.la",
		"gender": "Male",
		"phone": "581-856-5165",
		"dob": "9/30/1992"
	},
	{
		"id": 49,
		"fname": "Mitch",
		"lname": "Lammert",
		"email": "mlammert1c@list-manage.com",
		"gender": "Bigender",
		"phone": "604-164-0565",
		"dob": "8/6/1974"
	},
	{
		"id": 50,
		"fname": "Poul",
		"lname": "Spellesy",
		"email": "pspellesy1d@netlog.com",
		"gender": "Polygender",
		"phone": "780-782-6162",
		"dob": "1/23/1995"
	},
	{
		"id": 51,
		"fname": "Hinda",
		"lname": "Lantiff",
		"email": "hlantiff1e@blinklist.com",
		"gender": "Female",
		"phone": "973-763-8037",
		"dob": "2/23/1984"
	},
	{
		"id": 52,
		"fname": "Ernie",
		"lname": "Kiehnlt",
		"email": "ekiehnlt1f@google.co.jp",
		"gender": "Polygender",
		"phone": "698-317-5543",
		"dob": "11/17/2000"
	},
	{
		"id": 53,
		"fname": "Glori",
		"lname": "Le Noury",
		"email": "glenoury1g@blogtalkradio.com",
		"gender": "Agender",
		"phone": "127-730-4794",
		"dob": "6/12/1980"
	},
	{
		"id": 54,
		"fname": "Dayna",
		"lname": "Wadeling",
		"email": "dwadeling1h@cornell.edu",
		"gender": "Bigender",
		"phone": "594-541-8766",
		"dob": "1/27/1995"
	},
	{
		"id": 55,
		"fname": "Dore",
		"lname": "Soles",
		"email": "dsoles1i@virginia.edu",
		"gender": "Polygender",
		"phone": "228-191-8717",
		"dob": "3/31/2009"
	},
	{
		"id": 56,
		"fname": "Hercule",
		"lname": "MacIntosh",
		"email": "hmacintosh1j@google.com.br",
		"gender": "Agender",
		"phone": "496-817-1877",
		"dob": "11/12/1970"
	},
	{
		"id": 57,
		"fname": "Hedda",
		"lname": "Bellelli",
		"email": "hbellelli1k@cdc.gov",
		"gender": "Bigender",
		"phone": "203-963-6673",
		"dob": "1/14/2008"
	},
	{
		"id": 58,
		"fname": "Gustave",
		"lname": "McShane",
		"email": "gmcshane1l@wikipedia.org",
		"gender": "Genderfluid",
		"phone": "654-532-8268",
		"dob": "8/14/2003"
	},
	{
		"id": 59,
		"fname": "Zach",
		"lname": "Howler",
		"email": "zhowler1m@wp.com",
		"gender": "Agender",
		"phone": "176-504-4182",
		"dob": "12/4/1986"
	},
	{
		"id": 60,
		"fname": "Bettye",
		"lname": "MacLennan",
		"email": "bmaclennan1n@elpais.com",
		"gender": "Non-binary",
		"phone": "953-682-1535",
		"dob": "8/4/1999"
	},
	{
		"id": 61,
		"fname": "Stafford",
		"lname": "Garard",
		"email": "sgarard1o@bluehost.com",
		"gender": "Male",
		"phone": "717-940-6710",
		"dob": "7/2/1976"
	},
	{
		"id": 62,
		"fname": "Ros",
		"lname": "Stocker",
		"email": "rstocker1p@booking.com",
		"gender": "Bigender",
		"phone": "959-800-0933",
		"dob": "7/9/2004"
	},
	{
		"id": 63,
		"fname": "Ric",
		"lname": "Eatock",
		"email": "reatock1q@uiuc.edu",
		"gender": "Bigender",
		"phone": "787-428-5653",
		"dob": "4/24/1999"
	},
	{
		"id": 64,
		"fname": "Mickie",
		"lname": "Bielfelt",
		"email": "mbielfelt1r@webmd.com",
		"gender": "Female",
		"phone": "419-527-5132",
		"dob": "5/25/1989"
	},
	{
		"id": 65,
		"fname": "Ignacius",
		"lname": "Firks",
		"email": "ifirks1s@sun.com",
		"gender": "Female",
		"phone": "433-813-9284",
		"dob": "10/27/1995"
	},
	{
		"id": 66,
		"fname": "Wrennie",
		"lname": "Morgon",
		"email": "wmorgon1t@google.it",
		"gender": "Non-binary",
		"phone": "544-618-5745",
		"dob": "12/28/1987"
	},
	{
		"id": 67,
		"fname": "Lionello",
		"lname": "Grellier",
		"email": "lgrellier1u@ovh.net",
		"gender": "Bigender",
		"phone": "527-812-2017",
		"dob": "8/3/1980"
	},
	{
		"id": 68,
		"fname": "Gabriella",
		"lname": "Crat",
		"email": "gcrat1v@moonfruit.com",
		"gender": "Genderqueer",
		"phone": "943-376-3922",
		"dob": "1/10/1988"
	},
	{
		"id": 69,
		"fname": "Gennifer",
		"lname": "Tropman",
		"email": "gtropman1w@oaic.gov.au",
		"gender": "Bigender",
		"phone": "461-162-6311",
		"dob": "10/11/1987"
	},
	{
		"id": 70,
		"fname": "Creighton",
		"lname": "Brattan",
		"email": "cbrattan1x@xrea.com",
		"gender": "Genderqueer",
		"phone": "343-744-0372",
		"dob": "12/13/2002"
	},
	{
		"id": 71,
		"fname": "Sharia",
		"lname": "Satchel",
		"email": "ssatchel1y@engadget.com",
		"gender": "Genderqueer",
		"phone": "629-429-7953",
		"dob": "7/15/1987"
	},
	{
		"id": 72,
		"fname": "Trudie",
		"lname": "Stanlock",
		"email": "tstanlock1z@berkeley.edu",
		"gender": "Genderfluid",
		"phone": "697-338-3589",
		"dob": "4/17/1994"
	},
	{
		"id": 73,
		"fname": "Haily",
		"lname": "Denty",
		"email": "hdenty20@ftc.gov",
		"gender": "Male",
		"phone": "288-244-1682",
		"dob": "10/23/1975"
	},
	{
		"id": 74,
		"fname": "Giavani",
		"lname": "Rountree",
		"email": "grountree21@businessinsider.com",
		"gender": "Female",
		"phone": "892-959-8363",
		"dob": "10/19/1976"
	},
	{
		"id": 75,
		"fname": "Krishnah",
		"lname": "McManus",
		"email": "kmcmanus22@people.com.cn",
		"gender": "Agender",
		"phone": "381-261-7347",
		"dob": "5/26/1984"
	},
	{
		"id": 76,
		"fname": "Corrine",
		"lname": "Scrancher",
		"email": "cscrancher23@woothemes.com",
		"gender": "Genderqueer",
		"phone": "606-909-5709",
		"dob": "11/23/1988"
	},
	{
		"id": 77,
		"fname": "Chryste",
		"lname": "Strete",
		"email": "cstrete24@mediafire.com",
		"gender": "Female",
		"phone": "275-130-5353",
		"dob": "3/9/1976"
	},
	{
		"id": 78,
		"fname": "Carol",
		"lname": "Bernat",
		"email": "cbernat25@icio.us",
		"gender": "Male",
		"phone": "607-337-1969",
		"dob": "6/1/2004"
	},
	{
		"id": 79,
		"fname": "Richmound",
		"lname": "Martinson",
		"email": "rmartinson26@economist.com",
		"gender": "Male",
		"phone": "294-755-0107",
		"dob": "5/11/1993"
	},
	{
		"id": 80,
		"fname": "Mara",
		"lname": "Linny",
		"email": "mlinny27@dell.com",
		"gender": "Bigender",
		"phone": "438-543-8799",
		"dob": "10/15/1983"
	},
	{
		"id": 81,
		"fname": "Liza",
		"lname": "Kohlerman",
		"email": "lkohlerman28@google.ru",
		"gender": "Bigender",
		"phone": "996-766-5089",
		"dob": "10/17/2002"
	},
	{
		"id": 82,
		"fname": "Kanya",
		"lname": "Brun",
		"email": "kbrun29@comsenz.com",
		"gender": "Bigender",
		"phone": "484-558-0368",
		"dob": "10/8/1999"
	},
	{
		"id": 83,
		"fname": "Querida",
		"lname": "Gregon",
		"email": "qgregon2a@so-net.ne.jp",
		"gender": "Genderqueer",
		"phone": "137-570-4042",
		"dob": "8/3/1971"
	},
	{
		"id": 84,
		"fname": "Nelson",
		"lname": "Albon",
		"email": "nalbon2b@cbc.ca",
		"gender": "Genderfluid",
		"phone": "579-862-8222",
		"dob": "11/13/1980"
	},
	{
		"id": 85,
		"fname": "Kip",
		"lname": "Fathers",
		"email": "kfathers2c@umn.edu",
		"gender": "Genderfluid",
		"phone": "894-184-2873",
		"dob": "4/17/2001"
	},
	{
		"id": 86,
		"fname": "Allan",
		"lname": "Hughf",
		"email": "ahughf2d@bandcamp.com",
		"gender": "Genderfluid",
		"phone": "437-278-6645",
		"dob": "8/5/1986"
	},
	{
		"id": 87,
		"fname": "Harlan",
		"lname": "Rabat",
		"email": "hrabat2e@goodreads.com",
		"gender": "Bigender",
		"phone": "861-501-4780",
		"dob": "4/26/1984"
	},
	{
		"id": 88,
		"fname": "Ros",
		"lname": "Horder",
		"email": "rhorder2f@ca.gov",
		"gender": "Bigender",
		"phone": "458-578-2605",
		"dob": "10/23/1989"
	},
	{
		"id": 89,
		"fname": "Shaun",
		"lname": "Stemson",
		"email": "sstemson2g@dell.com",
		"gender": "Female",
		"phone": "647-281-8539",
		"dob": "9/18/1983"
	},
	{
		"id": 90,
		"fname": "Idalina",
		"lname": "Jaques",
		"email": "ijaques2h@digg.com",
		"gender": "Male",
		"phone": "192-134-1880",
		"dob": "6/21/2006"
	},
	{
		"id": 91,
		"fname": "Meg",
		"lname": "Fulcher",
		"email": "mfulcher2i@latimes.com",
		"gender": "Genderfluid",
		"phone": "498-432-6160",
		"dob": "6/14/1992"
	},
	{
		"id": 92,
		"fname": "Fanny",
		"lname": "Atty",
		"email": "fatty2j@alibaba.com",
		"gender": "Polygender",
		"phone": "792-354-0309",
		"dob": "1/21/1984"
	},
	{
		"id": 93,
		"fname": "Vernon",
		"lname": "Toye",
		"email": "vtoye2k@theglobeandmail.com",
		"gender": "Female",
		"phone": "738-181-8149",
		"dob": "9/13/1978"
	},
	{
		"id": 94,
		"fname": "Lea",
		"lname": "Broadstock",
		"email": "lbroadstock2l@rediff.com",
		"gender": "Genderqueer",
		"phone": "373-469-2029",
		"dob": "10/20/1975"
	},
	{
		"id": 95,
		"fname": "Jo ann",
		"lname": "Nelane",
		"email": "jnelane2m@yale.edu",
		"gender": "Polygender",
		"phone": "940-551-1587",
		"dob": "10/9/1993"
	},
	{
		"id": 96,
		"fname": "Lynn",
		"lname": "Hughs",
		"email": "lhughs2n@eventbrite.com",
		"gender": "Genderfluid",
		"phone": "658-790-9042",
		"dob": "8/25/1978"
	},
	{
		"id": 97,
		"fname": "Dena",
		"lname": "Jennaroy",
		"email": "djennaroy2o@imageshack.us",
		"gender": "Bigender",
		"phone": "594-310-4439",
		"dob": "3/8/2006"
	},
	{
		"id": 98,
		"fname": "Elianora",
		"lname": "Jobin",
		"email": "ejobin2p@answers.com",
		"gender": "Bigender",
		"phone": "653-725-9610",
		"dob": "9/12/1974"
	},
	{
		"id": 99,
		"fname": "Modesty",
		"lname": "Goggey",
		"email": "mgoggey2q@artisteer.com",
		"gender": "Polygender",
		"phone": "375-361-3615",
		"dob": "2/26/1973"
	},
	{
		"id": 100,
		"fname": "Markos",
		"lname": "Cankett",
		"email": "mcankett2r@sitemeter.com",
		"gender": "Non-binary",
		"phone": "863-991-7179",
		"dob": "6/23/1995"
	},
	{
		"id": 101,
		"fname": "Alana",
		"lname": "Ridwood",
		"email": "aridwood2s@furl.net",
		"gender": "Genderqueer",
		"phone": "535-787-1402",
		"dob": "10/11/1992"
	},
	{
		"id": 102,
		"fname": "Adora",
		"lname": "Hassekl",
		"email": "ahassekl2t@jimdo.com",
		"gender": "Polygender",
		"phone": "824-928-9198",
		"dob": "1/2/1977"
	},
	{
		"id": 103,
		"fname": "Gawen",
		"lname": "Sillett",
		"email": "gsillett2u@blinklist.com",
		"gender": "Agender",
		"phone": "296-338-8722",
		"dob": "11/28/2008"
	},
	{
		"id": 104,
		"fname": "Audie",
		"lname": "MacMichael",
		"email": "amacmichael2v@vistaprint.com",
		"gender": "Polygender",
		"phone": "462-875-4661",
		"dob": "10/20/1989"
	},
	{
		"id": 105,
		"fname": "Dode",
		"lname": "Keddey",
		"email": "dkeddey2w@tiny.cc",
		"gender": "Female",
		"phone": "973-793-8587",
		"dob": "5/10/1991"
	},
	{
		"id": 106,
		"fname": "Rayshell",
		"lname": "Connochie",
		"email": "rconnochie2x@storify.com",
		"gender": "Polygender",
		"phone": "755-749-6697",
		"dob": "11/25/1972"
	},
	{
		"id": 107,
		"fname": "Rosanne",
		"lname": "Gallihawk",
		"email": "rgallihawk2y@nydailynews.com",
		"gender": "Polygender",
		"phone": "822-552-2975",
		"dob": "8/29/1990"
	},
	{
		"id": 108,
		"fname": "Norma",
		"lname": "Alven",
		"email": "nalven2z@seesaa.net",
		"gender": "Genderfluid",
		"phone": "468-639-6773",
		"dob": "9/12/1971"
	},
	{
		"id": 109,
		"fname": "Salmon",
		"lname": "Hardingham",
		"email": "shardingham30@wp.com",
		"gender": "Male",
		"phone": "414-557-4222",
		"dob": "3/27/1976"
	},
	{
		"id": 110,
		"fname": "Lon",
		"lname": "Manuello",
		"email": "lmanuello31@harvard.edu",
		"gender": "Genderfluid",
		"phone": "839-261-9491",
		"dob": "9/3/1984"
	},
	{
		"id": 111,
		"fname": "Lizette",
		"lname": "Flobert",
		"email": "lflobert32@amazon.com",
		"gender": "Male",
		"phone": "136-155-7567",
		"dob": "12/26/1984"
	},
	{
		"id": 112,
		"fname": "Urbain",
		"lname": "Dagworthy",
		"email": "udagworthy33@linkedin.com",
		"gender": "Polygender",
		"phone": "611-889-3349",
		"dob": "11/28/1996"
	},
	{
		"id": 113,
		"fname": "Wilone",
		"lname": "Scholes",
		"email": "wscholes34@ucoz.ru",
		"gender": "Bigender",
		"phone": "455-181-7152",
		"dob": "4/29/1996"
	},
	{
		"id": 114,
		"fname": "Salome",
		"lname": "Downham",
		"email": "sdownham35@skyrock.com",
		"gender": "Polygender",
		"phone": "281-910-7319",
		"dob": "6/3/1981"
	},
	{
		"id": 115,
		"fname": "Gerrilee",
		"lname": "Pawfoot",
		"email": "gpawfoot36@ameblo.jp",
		"gender": "Female",
		"phone": "275-996-1863",
		"dob": "4/17/1975"
	},
	{
		"id": 116,
		"fname": "Rad",
		"lname": "Bawme",
		"email": "rbawme37@guardian.co.uk",
		"gender": "Female",
		"phone": "666-676-5932",
		"dob": "7/6/1988"
	},
	{
		"id": 117,
		"fname": "Dieter",
		"lname": "Pinniger",
		"email": "dpinniger38@geocities.jp",
		"gender": "Genderqueer",
		"phone": "422-759-0293",
		"dob": "1/19/1978"
	},
	{
		"id": 118,
		"fname": "Daveta",
		"lname": "Gussie",
		"email": "dgussie39@dot.gov",
		"gender": "Non-binary",
		"phone": "982-478-3553",
		"dob": "2/15/1985"
	},
	{
		"id": 119,
		"fname": "Horatio",
		"lname": "Dedmam",
		"email": "hdedmam3a@ft.com",
		"gender": "Polygender",
		"phone": "899-956-1427",
		"dob": "9/27/1996"
	},
	{
		"id": 120,
		"fname": "Tresa",
		"lname": "Cristofano",
		"email": "tcristofano3b@huffingtonpost.com",
		"gender": "Female",
		"phone": "786-496-6519",
		"dob": "7/22/1974"
	},
	{
		"id": 121,
		"fname": "Clayborn",
		"lname": "Arkow",
		"email": "carkow3c@weibo.com",
		"gender": "Bigender",
		"phone": "415-391-0742",
		"dob": "12/6/2005"
	},
	{
		"id": 122,
		"fname": "Tully",
		"lname": "Trolley",
		"email": "ttrolley3d@ed.gov",
		"gender": "Genderqueer",
		"phone": "881-938-2401",
		"dob": "6/19/2007"
	},
	{
		"id": 123,
		"fname": "Corine",
		"lname": "Kauschke",
		"email": "ckauschke3e@usa.gov",
		"gender": "Genderqueer",
		"phone": "779-583-5295",
		"dob": "2/4/1988"
	},
	{
		"id": 124,
		"fname": "Juieta",
		"lname": "Goodlip",
		"email": "jgoodlip3f@plala.or.jp",
		"gender": "Genderqueer",
		"phone": "910-231-4997",
		"dob": "4/13/1974"
	},
	{
		"id": 125,
		"fname": "Dill",
		"lname": "Casswell",
		"email": "dcasswell3g@bloglines.com",
		"gender": "Genderfluid",
		"phone": "227-955-2863",
		"dob": "4/9/1995"
	},
	{
		"id": 126,
		"fname": "Ralina",
		"lname": "Fennessy",
		"email": "rfennessy3h@forbes.com",
		"gender": "Non-binary",
		"phone": "255-144-1771",
		"dob": "5/15/1980"
	},
	{
		"id": 127,
		"fname": "Jackson",
		"lname": "Currey",
		"email": "jcurrey3i@wufoo.com",
		"gender": "Female",
		"phone": "522-147-3525",
		"dob": "11/26/1990"
	},
	{
		"id": 128,
		"fname": "Wang",
		"lname": "Dominiak",
		"email": "wdominiak3j@imageshack.us",
		"gender": "Male",
		"phone": "388-575-3258",
		"dob": "11/11/1996"
	},
	{
		"id": 129,
		"fname": "Hetti",
		"lname": "Iacovozzo",
		"email": "hiacovozzo3k@amazonaws.com",
		"gender": "Non-binary",
		"phone": "345-804-5051",
		"dob": "3/31/2010"
	},
	{
		"id": 130,
		"fname": "Waylen",
		"lname": "Jallin",
		"email": "wjallin3l@blogs.com",
		"gender": "Bigender",
		"phone": "902-338-8215",
		"dob": "1/6/2008"
	},
	{
		"id": 131,
		"fname": "Elyn",
		"lname": "Bunford",
		"email": "ebunford3m@umn.edu",
		"gender": "Female",
		"phone": "463-402-7369",
		"dob": "2/28/1971"
	},
	{
		"id": 132,
		"fname": "Mortie",
		"lname": "Learmont",
		"email": "mlearmont3n@jugem.jp",
		"gender": "Non-binary",
		"phone": "870-147-5659",
		"dob": "5/15/1974"
	},
	{
		"id": 133,
		"fname": "Marrilee",
		"lname": "Newns",
		"email": "mnewns3o@techcrunch.com",
		"gender": "Female",
		"phone": "561-352-7736",
		"dob": "1/16/2008"
	},
	{
		"id": 134,
		"fname": "Reta",
		"lname": "Kinsella",
		"email": "rkinsella3p@instagram.com",
		"gender": "Female",
		"phone": "324-793-2886",
		"dob": "8/9/1998"
	},
	{
		"id": 135,
		"fname": "Gwen",
		"lname": "O'Carmody",
		"email": "gocarmody3q@wisc.edu",
		"gender": "Male",
		"phone": "985-318-5625",
		"dob": "7/24/2000"
	},
	{
		"id": 136,
		"fname": "Courtney",
		"lname": "Borrington",
		"email": "cborrington3r@bloomberg.com",
		"gender": "Bigender",
		"phone": "454-196-5119",
		"dob": "7/16/1998"
	},
	{
		"id": 137,
		"fname": "Adria",
		"lname": "Flett",
		"email": "aflett3s@flickr.com",
		"gender": "Non-binary",
		"phone": "766-576-3993",
		"dob": "8/7/1998"
	},
	{
		"id": 138,
		"fname": "Eloisa",
		"lname": "Ridder",
		"email": "eridder3t@miibeian.gov.cn",
		"gender": "Genderfluid",
		"phone": "957-930-7081",
		"dob": "6/1/2007"
	},
	{
		"id": 139,
		"fname": "Currey",
		"lname": "Paulin",
		"email": "cpaulin3u@chron.com",
		"gender": "Genderqueer",
		"phone": "561-650-0678",
		"dob": "9/2/2007"
	},
	{
		"id": 140,
		"fname": "Jobi",
		"lname": "Dreakin",
		"email": "jdreakin3v@dot.gov",
		"gender": "Polygender",
		"phone": "333-859-9257",
		"dob": "6/7/2005"
	},
	{
		"id": 141,
		"fname": "Bobina",
		"lname": "Hince",
		"email": "bhince3w@wikia.com",
		"gender": "Polygender",
		"phone": "231-288-2388",
		"dob": "11/12/1974"
	},
	{
		"id": 142,
		"fname": "Aubrie",
		"lname": "Tummasutti",
		"email": "atummasutti3x@trellian.com",
		"gender": "Male",
		"phone": "852-554-0297",
		"dob": "11/2/1980"
	},
	{
		"id": 143,
		"fname": "Seana",
		"lname": "McMinn",
		"email": "smcminn3y@buzzfeed.com",
		"gender": "Agender",
		"phone": "815-731-9823",
		"dob": "5/30/2007"
	},
	{
		"id": 144,
		"fname": "Ladonna",
		"lname": "Kilford",
		"email": "lkilford3z@mashable.com",
		"gender": "Bigender",
		"phone": "794-482-3820",
		"dob": "7/6/1997"
	},
	{
		"id": 145,
		"fname": "Hoyt",
		"lname": "Karby",
		"email": "hkarby40@zimbio.com",
		"gender": "Male",
		"phone": "229-883-8532",
		"dob": "2/24/1972"
	},
	{
		"id": 146,
		"fname": "Gabi",
		"lname": "Djorevic",
		"email": "gdjorevic41@liveinternet.ru",
		"gender": "Non-binary",
		"phone": "518-561-6307",
		"dob": "4/23/1983"
	},
	{
		"id": 147,
		"fname": "Roana",
		"lname": "Bernhard",
		"email": "rbernhard42@cocolog-nifty.com",
		"gender": "Non-binary",
		"phone": "150-122-9212",
		"dob": "11/3/1994"
	},
	{
		"id": 148,
		"fname": "Alister",
		"lname": "Vines",
		"email": "avines43@noaa.gov",
		"gender": "Non-binary",
		"phone": "656-869-2756",
		"dob": "7/24/1997"
	},
	{
		"id": 149,
		"fname": "Bealle",
		"lname": "Kurdani",
		"email": "bkurdani44@washington.edu",
		"gender": "Non-binary",
		"phone": "865-378-0951",
		"dob": "12/3/1987"
	},
	{
		"id": 150,
		"fname": "Shane",
		"lname": "O'Scollain",
		"email": "soscollain45@who.int",
		"gender": "Genderfluid",
		"phone": "656-181-4653",
		"dob": "1/1/2005"
	},
	{
		"id": 151,
		"fname": "Wenda",
		"lname": "Grandisson",
		"email": "wgrandisson46@blogspot.com",
		"gender": "Female",
		"phone": "567-459-1058",
		"dob": "3/20/2008"
	},
	{
		"id": 152,
		"fname": "Greg",
		"lname": "Peart",
		"email": "gpeart47@shutterfly.com",
		"gender": "Non-binary",
		"phone": "510-151-3774",
		"dob": "12/19/1973"
	},
	{
		"id": 153,
		"fname": "Corissa",
		"lname": "Station",
		"email": "cstation48@un.org",
		"gender": "Male",
		"phone": "914-864-5742",
		"dob": "6/20/2005"
	},
	{
		"id": 154,
		"fname": "Marnia",
		"lname": "Buffham",
		"email": "mbuffham49@canalblog.com",
		"gender": "Polygender",
		"phone": "632-913-0930",
		"dob": "12/14/1987"
	},
	{
		"id": 155,
		"fname": "Bobinette",
		"lname": "La Padula",
		"email": "blapadula4a@earthlink.net",
		"gender": "Genderfluid",
		"phone": "254-635-5067",
		"dob": "9/14/1998"
	},
	{
		"id": 156,
		"fname": "Scarlett",
		"lname": "Blakes",
		"email": "sblakes4b@facebook.com",
		"gender": "Female",
		"phone": "989-192-0797",
		"dob": "3/19/2009"
	},
	{
		"id": 157,
		"fname": "Selina",
		"lname": "Dymond",
		"email": "sdymond4c@barnesandnoble.com",
		"gender": "Agender",
		"phone": "937-342-0762",
		"dob": "9/8/1973"
	},
	{
		"id": 158,
		"fname": "Adriaens",
		"lname": "Caveney",
		"email": "acaveney4d@google.es",
		"gender": "Female",
		"phone": "730-952-6350",
		"dob": "7/24/1997"
	},
	{
		"id": 159,
		"fname": "Clio",
		"lname": "Rhubottom",
		"email": "crhubottom4e@cbsnews.com",
		"gender": "Male",
		"phone": "612-746-0848",
		"dob": "1/4/1974"
	},
	{
		"id": 160,
		"fname": "Nadeen",
		"lname": "Petrichat",
		"email": "npetrichat4f@vimeo.com",
		"gender": "Female",
		"phone": "452-862-9971",
		"dob": "6/7/1993"
	},
	{
		"id": 161,
		"fname": "Philippine",
		"lname": "Chuter",
		"email": "pchuter4g@ask.com",
		"gender": "Male",
		"phone": "633-699-8029",
		"dob": "4/2/1984"
	},
	{
		"id": 162,
		"fname": "Garv",
		"lname": "Mogenot",
		"email": "gmogenot4h@friendfeed.com",
		"gender": "Bigender",
		"phone": "320-330-9505",
		"dob": "1/18/2006"
	},
	{
		"id": 163,
		"fname": "Caro",
		"lname": "Keaveney",
		"email": "ckeaveney4i@mozilla.com",
		"gender": "Polygender",
		"phone": "801-352-8081",
		"dob": "5/27/1985"
	},
	{
		"id": 164,
		"fname": "Cosmo",
		"lname": "Crimpe",
		"email": "ccrimpe4j@opera.com",
		"gender": "Male",
		"phone": "140-403-7573",
		"dob": "6/23/2001"
	},
	{
		"id": 165,
		"fname": "Sheri",
		"lname": "Ellor",
		"email": "sellor4k@huffingtonpost.com",
		"gender": "Polygender",
		"phone": "251-524-7652",
		"dob": "1/18/2006"
	},
	{
		"id": 166,
		"fname": "Ophelie",
		"lname": "Moore",
		"email": "omoore4l@elpais.com",
		"gender": "Male",
		"phone": "780-852-0069",
		"dob": "7/23/2000"
	},
	{
		"id": 167,
		"fname": "Adams",
		"lname": "Noen",
		"email": "anoen4m@loc.gov",
		"gender": "Polygender",
		"phone": "791-645-3823",
		"dob": "9/4/1990"
	},
	{
		"id": 168,
		"fname": "Danell",
		"lname": "Quarrell",
		"email": "dquarrell4n@indiegogo.com",
		"gender": "Polygender",
		"phone": "442-522-2722",
		"dob": "10/22/2010"
	},
	{
		"id": 169,
		"fname": "Jeremias",
		"lname": "Maidens",
		"email": "jmaidens4o@example.com",
		"gender": "Non-binary",
		"phone": "274-402-4575",
		"dob": "1/20/2001"
	},
	{
		"id": 170,
		"fname": "Welby",
		"lname": "Bruyet",
		"email": "wbruyet4p@hhs.gov",
		"gender": "Genderfluid",
		"phone": "992-770-2379",
		"dob": "6/3/1981"
	},
	{
		"id": 171,
		"fname": "Pauletta",
		"lname": "Punchard",
		"email": "ppunchard4q@blogspot.com",
		"gender": "Non-binary",
		"phone": "834-947-9890",
		"dob": "3/10/1971"
	},
	{
		"id": 172,
		"fname": "Willy",
		"lname": "Lightman",
		"email": "wlightman4r@newsvine.com",
		"gender": "Genderfluid",
		"phone": "801-481-9857",
		"dob": "12/7/1996"
	},
	{
		"id": 173,
		"fname": "Brnaba",
		"lname": "Padley",
		"email": "bpadley4s@themeforest.net",
		"gender": "Male",
		"phone": "880-519-6342",
		"dob": "5/17/2005"
	},
	{
		"id": 174,
		"fname": "Ennis",
		"lname": "Hugle",
		"email": "ehugle4t@nhs.uk",
		"gender": "Non-binary",
		"phone": "123-146-2008",
		"dob": "5/2/1988"
	},
	{
		"id": 175,
		"fname": "Kari",
		"lname": "Rawling",
		"email": "krawling4u@patch.com",
		"gender": "Genderqueer",
		"phone": "258-918-1678",
		"dob": "5/21/2006"
	},
	{
		"id": 176,
		"fname": "Augusto",
		"lname": "Schieferstein",
		"email": "aschieferstein4v@examiner.com",
		"gender": "Non-binary",
		"phone": "606-212-5169",
		"dob": "5/1/1974"
	},
	{
		"id": 177,
		"fname": "Torin",
		"lname": "McBryde",
		"email": "tmcbryde4w@ucsd.edu",
		"gender": "Male",
		"phone": "470-772-9374",
		"dob": "4/23/1984"
	},
	{
		"id": 178,
		"fname": "Yvon",
		"lname": "Crawforth",
		"email": "ycrawforth4x@google.cn",
		"gender": "Female",
		"phone": "536-373-3400",
		"dob": "4/19/1984"
	},
	{
		"id": 179,
		"fname": "Bessy",
		"lname": "Lorinez",
		"email": "blorinez4y@senate.gov",
		"gender": "Polygender",
		"phone": "784-256-1033",
		"dob": "4/6/1976"
	},
	{
		"id": 180,
		"fname": "Patrica",
		"lname": "Fearnley",
		"email": "pfearnley4z@si.edu",
		"gender": "Agender",
		"phone": "592-644-7553",
		"dob": "9/30/1988"
	},
	{
		"id": 181,
		"fname": "Sherlocke",
		"lname": "Entreis",
		"email": "sentreis50@wsj.com",
		"gender": "Female",
		"phone": "794-108-5512",
		"dob": "5/19/2002"
	},
	{
		"id": 182,
		"fname": "Othilie",
		"lname": "Jedraszczyk",
		"email": "ojedraszczyk51@4shared.com",
		"gender": "Male",
		"phone": "547-529-6210",
		"dob": "3/23/1975"
	},
	{
		"id": 183,
		"fname": "Irv",
		"lname": "Dufaire",
		"email": "idufaire52@hud.gov",
		"gender": "Agender",
		"phone": "300-259-7601",
		"dob": "10/24/1971"
	},
	{
		"id": 184,
		"fname": "Birgitta",
		"lname": "Whetland",
		"email": "bwhetland53@lulu.com",
		"gender": "Genderqueer",
		"phone": "125-554-8479",
		"dob": "7/16/2006"
	},
	{
		"id": 185,
		"fname": "Kathlin",
		"lname": "Longrigg",
		"email": "klongrigg54@sun.com",
		"gender": "Non-binary",
		"phone": "233-607-1412",
		"dob": "8/2/1994"
	},
	{
		"id": 186,
		"fname": "Manda",
		"lname": "Kleinstein",
		"email": "mkleinstein55@freewebs.com",
		"gender": "Non-binary",
		"phone": "238-216-4807",
		"dob": "1/9/1974"
	},
	{
		"id": 187,
		"fname": "Hannis",
		"lname": "MacKnocker",
		"email": "hmacknocker56@unesco.org",
		"gender": "Polygender",
		"phone": "463-992-9917",
		"dob": "10/26/1982"
	},
	{
		"id": 188,
		"fname": "Brocky",
		"lname": "Bywater",
		"email": "bbywater57@abc.net.au",
		"gender": "Genderqueer",
		"phone": "554-667-4835",
		"dob": "5/21/1981"
	},
	{
		"id": 189,
		"fname": "Priscilla",
		"lname": "Grimsditch",
		"email": "pgrimsditch58@netscape.com",
		"gender": "Male",
		"phone": "425-867-1366",
		"dob": "8/20/2002"
	},
	{
		"id": 190,
		"fname": "Meghan",
		"lname": "Guest",
		"email": "mguest59@dot.gov",
		"gender": "Genderqueer",
		"phone": "308-624-2492",
		"dob": "6/11/1974"
	},
	{
		"id": 191,
		"fname": "Orrin",
		"lname": "Eisikowitch",
		"email": "oeisikowitch5a@gov.uk",
		"gender": "Genderfluid",
		"phone": "202-660-8953",
		"dob": "1/17/1989"
	},
	{
		"id": 192,
		"fname": "Eli",
		"lname": "Boyes",
		"email": "eboyes5b@github.com",
		"gender": "Bigender",
		"phone": "325-273-2402",
		"dob": "11/27/1984"
	},
	{
		"id": 193,
		"fname": "Tremain",
		"lname": "Oehme",
		"email": "toehme5c@mediafire.com",
		"gender": "Genderqueer",
		"phone": "752-286-8259",
		"dob": "7/21/1983"
	},
	{
		"id": 194,
		"fname": "Dagmar",
		"lname": "Hacquard",
		"email": "dhacquard5d@qq.com",
		"gender": "Bigender",
		"phone": "210-172-2251",
		"dob": "9/4/1982"
	},
	{
		"id": 195,
		"fname": "Dani",
		"lname": "Normavill",
		"email": "dnormavill5e@tmall.com",
		"gender": "Female",
		"phone": "163-180-7838",
		"dob": "7/31/1975"
	},
	{
		"id": 196,
		"fname": "Darryl",
		"lname": "Carnson",
		"email": "dcarnson5f@google.pl",
		"gender": "Genderqueer",
		"phone": "957-368-2027",
		"dob": "5/20/1998"
	},
	{
		"id": 197,
		"fname": "Alexandre",
		"lname": "Gutherson",
		"email": "agutherson5g@typepad.com",
		"gender": "Genderfluid",
		"phone": "496-556-4975",
		"dob": "5/6/1982"
	},
	{
		"id": 198,
		"fname": "Fredia",
		"lname": "Sollom",
		"email": "fsollom5h@cbsnews.com",
		"gender": "Genderqueer",
		"phone": "568-613-9716",
		"dob": "4/14/1972"
	},
	{
		"id": 199,
		"fname": "Vitoria",
		"lname": "Oppery",
		"email": "voppery5i@ca.gov",
		"gender": "Genderfluid",
		"phone": "179-275-2959",
		"dob": "8/4/1996"
	},
	{
		"id": 200,
		"fname": "Meredith",
		"lname": "Shimmans",
		"email": "mshimmans5j@ucoz.ru",
		"gender": "Polygender",
		"phone": "585-667-0906",
		"dob": "4/20/1976"
	},
	{
		"id": 201,
		"fname": "Donovan",
		"lname": "Antonikov",
		"email": "dantonikov5k@usda.gov",
		"gender": "Polygender",
		"phone": "317-474-2325",
		"dob": "8/15/2005"
	},
	{
		"id": 202,
		"fname": "Heather",
		"lname": "Early",
		"email": "hearly5l@nasa.gov",
		"gender": "Non-binary",
		"phone": "133-113-3263",
		"dob": "9/30/2009"
	},
	{
		"id": 203,
		"fname": "Abey",
		"lname": "O'Dougherty",
		"email": "aodougherty5m@dmoz.org",
		"gender": "Female",
		"phone": "471-840-0666",
		"dob": "11/11/2009"
	},
	{
		"id": 204,
		"fname": "Westbrooke",
		"lname": "Matteacci",
		"email": "wmatteacci5n@adobe.com",
		"gender": "Genderfluid",
		"phone": "578-555-2053",
		"dob": "7/12/1975"
	},
	{
		"id": 205,
		"fname": "Jasper",
		"lname": "Gundrey",
		"email": "jgundrey5o@meetup.com",
		"gender": "Bigender",
		"phone": "888-815-6901",
		"dob": "11/6/2001"
	},
	{
		"id": 206,
		"fname": "Cornie",
		"lname": "Genthner",
		"email": "cgenthner5p@cpanel.net",
		"gender": "Male",
		"phone": "560-850-6968",
		"dob": "4/2/1997"
	},
	{
		"id": 207,
		"fname": "Celinka",
		"lname": "Connikie",
		"email": "cconnikie5q@gravatar.com",
		"gender": "Non-binary",
		"phone": "470-942-4775",
		"dob": "2/3/2007"
	},
	{
		"id": 208,
		"fname": "Aurea",
		"lname": "Robbs",
		"email": "arobbs5r@myspace.com",
		"gender": "Genderfluid",
		"phone": "812-659-5088",
		"dob": "4/26/2000"
	},
	{
		"id": 209,
		"fname": "Marnia",
		"lname": "Marchant",
		"email": "mmarchant5s@wufoo.com",
		"gender": "Genderqueer",
		"phone": "451-890-9004",
		"dob": "6/11/1978"
	},
	{
		"id": 210,
		"fname": "Ephraim",
		"lname": "Sanday",
		"email": "esanday5t@youku.com",
		"gender": "Genderfluid",
		"phone": "882-453-4151",
		"dob": "9/20/2007"
	},
	{
		"id": 211,
		"fname": "Ricard",
		"lname": "Willwood",
		"email": "rwillwood5u@dropbox.com",
		"gender": "Genderfluid",
		"phone": "401-957-4946",
		"dob": "12/4/2006"
	},
	{
		"id": 212,
		"fname": "Bram",
		"lname": "Donnett",
		"email": "bdonnett5v@cnbc.com",
		"gender": "Non-binary",
		"phone": "789-733-7733",
		"dob": "3/12/2006"
	},
	{
		"id": 213,
		"fname": "Arin",
		"lname": "Lagen",
		"email": "alagen5w@cloudflare.com",
		"gender": "Agender",
		"phone": "871-939-8996",
		"dob": "6/8/1999"
	},
	{
		"id": 214,
		"fname": "Damiano",
		"lname": "Noyce",
		"email": "dnoyce5x@loc.gov",
		"gender": "Male",
		"phone": "707-351-2326",
		"dob": "12/29/1995"
	},
	{
		"id": 215,
		"fname": "Peria",
		"lname": "Greenleaf",
		"email": "pgreenleaf5y@utexas.edu",
		"gender": "Genderqueer",
		"phone": "626-997-8644",
		"dob": "10/13/1977"
	},
	{
		"id": 216,
		"fname": "Richie",
		"lname": "Inchley",
		"email": "rinchley5z@ihg.com",
		"gender": "Female",
		"phone": "970-658-7924",
		"dob": "3/30/1997"
	},
	{
		"id": 217,
		"fname": "Cilka",
		"lname": "Webby",
		"email": "cwebby60@skyrock.com",
		"gender": "Agender",
		"phone": "546-224-6314",
		"dob": "1/23/2010"
	},
	{
		"id": 218,
		"fname": "Francesco",
		"lname": "Bredee",
		"email": "fbredee61@dailymail.co.uk",
		"gender": "Bigender",
		"phone": "178-848-3931",
		"dob": "5/6/1974"
	},
	{
		"id": 219,
		"fname": "Janela",
		"lname": "Aymerich",
		"email": "jaymerich62@bbb.org",
		"gender": "Agender",
		"phone": "380-337-6896",
		"dob": "11/9/1995"
	},
	{
		"id": 220,
		"fname": "Morley",
		"lname": "Presley",
		"email": "mpresley63@spiegel.de",
		"gender": "Bigender",
		"phone": "836-234-9546",
		"dob": "3/4/2004"
	},
	{
		"id": 221,
		"fname": "Jacki",
		"lname": "Welfare",
		"email": "jwelfare64@columbia.edu",
		"gender": "Genderqueer",
		"phone": "492-600-1571",
		"dob": "5/18/1993"
	},
	{
		"id": 222,
		"fname": "Emanuele",
		"lname": "Antunez",
		"email": "eantunez65@accuweather.com",
		"gender": "Male",
		"phone": "164-889-8462",
		"dob": "9/2/1979"
	},
	{
		"id": 223,
		"fname": "Marten",
		"lname": "Rubinshtein",
		"email": "mrubinshtein66@oakley.com",
		"gender": "Genderfluid",
		"phone": "397-261-9550",
		"dob": "2/11/1989"
	},
	{
		"id": 224,
		"fname": "Dirk",
		"lname": "Powder",
		"email": "dpowder67@japanpost.jp",
		"gender": "Genderfluid",
		"phone": "113-433-9578",
		"dob": "3/3/1975"
	},
	{
		"id": 225,
		"fname": "Nevin",
		"lname": "Bowen",
		"email": "nbowen68@list-manage.com",
		"gender": "Bigender",
		"phone": "592-644-3364",
		"dob": "11/8/2008"
	},
	{
		"id": 226,
		"fname": "Matthias",
		"lname": "Cuss",
		"email": "mcuss69@skype.com",
		"gender": "Bigender",
		"phone": "839-205-6199",
		"dob": "5/19/1971"
	},
	{
		"id": 227,
		"fname": "Jasun",
		"lname": "Mewes",
		"email": "jmewes6a@indiatimes.com",
		"gender": "Female",
		"phone": "820-354-9658",
		"dob": "8/20/1987"
	},
	{
		"id": 228,
		"fname": "Eleanor",
		"lname": "McLese",
		"email": "emclese6b@jugem.jp",
		"gender": "Genderfluid",
		"phone": "229-892-7122",
		"dob": "12/2/1979"
	},
	{
		"id": 229,
		"fname": "Swen",
		"lname": "Delieu",
		"email": "sdelieu6c@myspace.com",
		"gender": "Genderqueer",
		"phone": "750-125-5018",
		"dob": "4/4/1978"
	},
	{
		"id": 230,
		"fname": "Nollie",
		"lname": "Borges",
		"email": "nborges6d@tinypic.com",
		"gender": "Agender",
		"phone": "254-115-9436",
		"dob": "11/22/1982"
	},
	{
		"id": 231,
		"fname": "Cullin",
		"lname": "Eliassen",
		"email": "celiassen6e@1688.com",
		"gender": "Polygender",
		"phone": "493-196-5236",
		"dob": "11/18/1973"
	},
	{
		"id": 232,
		"fname": "Adelbert",
		"lname": "Velareal",
		"email": "avelareal6f@nps.gov",
		"gender": "Non-binary",
		"phone": "563-695-1301",
		"dob": "9/9/1994"
	},
	{
		"id": 233,
		"fname": "Gus",
		"lname": "Motte",
		"email": "gmotte6g@nyu.edu",
		"gender": "Genderqueer",
		"phone": "857-284-5875",
		"dob": "11/26/1984"
	},
	{
		"id": 234,
		"fname": "Kinsley",
		"lname": "Holdworth",
		"email": "kholdworth6h@i2i.jp",
		"gender": "Bigender",
		"phone": "641-770-3164",
		"dob": "5/13/2005"
	},
	{
		"id": 235,
		"fname": "Kaela",
		"lname": "Poulglais",
		"email": "kpoulglais6i@4shared.com",
		"gender": "Female",
		"phone": "518-250-1235",
		"dob": "1/8/1991"
	},
	{
		"id": 236,
		"fname": "Sterling",
		"lname": "Finlay",
		"email": "sfinlay6j@bloglovin.com",
		"gender": "Non-binary",
		"phone": "246-612-7691",
		"dob": "6/28/1981"
	},
	{
		"id": 237,
		"fname": "Aeriela",
		"lname": "McGarvie",
		"email": "amcgarvie6k@sun.com",
		"gender": "Genderqueer",
		"phone": "401-635-2653",
		"dob": "8/30/1988"
	},
	{
		"id": 238,
		"fname": "Melli",
		"lname": "Whitmarsh",
		"email": "mwhitmarsh6l@scientificamerican.com",
		"gender": "Non-binary",
		"phone": "631-324-9798",
		"dob": "2/6/1987"
	},
	{
		"id": 239,
		"fname": "Shantee",
		"lname": "Beckingham",
		"email": "sbeckingham6m@wiley.com",
		"gender": "Agender",
		"phone": "784-163-3294",
		"dob": "3/9/2006"
	},
	{
		"id": 240,
		"fname": "Angie",
		"lname": "Hoyte",
		"email": "ahoyte6n@army.mil",
		"gender": "Agender",
		"phone": "342-235-6650",
		"dob": "6/17/2003"
	},
	{
		"id": 241,
		"fname": "Annadiane",
		"lname": "MacMaster",
		"email": "amacmaster6o@nytimes.com",
		"gender": "Genderqueer",
		"phone": "408-549-0628",
		"dob": "10/11/2009"
	},
	{
		"id": 242,
		"fname": "Judon",
		"lname": "Janew",
		"email": "jjanew6p@google.com.au",
		"gender": "Agender",
		"phone": "372-785-7002",
		"dob": "7/24/1980"
	},
	{
		"id": 243,
		"fname": "Leonard",
		"lname": "Godney",
		"email": "lgodney6q@nsw.gov.au",
		"gender": "Non-binary",
		"phone": "163-561-7361",
		"dob": "8/14/1978"
	},
	{
		"id": 244,
		"fname": "Kimmy",
		"lname": "Nelthrop",
		"email": "knelthrop6r@wsj.com",
		"gender": "Genderfluid",
		"phone": "946-543-1601",
		"dob": "12/1/2008"
	},
	{
		"id": 245,
		"fname": "Jessica",
		"lname": "Norsworthy",
		"email": "jnorsworthy6s@ovh.net",
		"gender": "Female",
		"phone": "593-459-3702",
		"dob": "6/23/1989"
	},
	{
		"id": 246,
		"fname": "Junia",
		"lname": "Brauns",
		"email": "jbrauns6t@xing.com",
		"gender": "Male",
		"phone": "708-854-2106",
		"dob": "2/4/2009"
	},
	{
		"id": 247,
		"fname": "Christabella",
		"lname": "Helwig",
		"email": "chelwig6u@tumblr.com",
		"gender": "Non-binary",
		"phone": "820-574-3385",
		"dob": "8/19/1993"
	},
	{
		"id": 248,
		"fname": "Saundra",
		"lname": "Zannelli",
		"email": "szannelli6v@google.es",
		"gender": "Non-binary",
		"phone": "355-851-4330",
		"dob": "12/8/1987"
	},
	{
		"id": 249,
		"fname": "Franciska",
		"lname": "Corneliussen",
		"email": "fcorneliussen6w@digg.com",
		"gender": "Agender",
		"phone": "685-196-2449",
		"dob": "4/22/2007"
	},
	{
		"id": 250,
		"fname": "Sigvard",
		"lname": "MacCahey",
		"email": "smaccahey6x@google.com.au",
		"gender": "Polygender",
		"phone": "826-918-8581",
		"dob": "5/4/1978"
	},
	{
		"id": 251,
		"fname": "Marita",
		"lname": "Latty",
		"email": "mlatty6y@reference.com",
		"gender": "Non-binary",
		"phone": "928-117-0203",
		"dob": "12/21/1982"
	},
	{
		"id": 252,
		"fname": "Mallory",
		"lname": "Peschke",
		"email": "mpeschke6z@ovh.net",
		"gender": "Genderfluid",
		"phone": "112-535-1848",
		"dob": "1/15/1987"
	},
	{
		"id": 253,
		"fname": "Latashia",
		"lname": "O'Coskerry",
		"email": "locoskerry70@google.pl",
		"gender": "Agender",
		"phone": "558-635-8958",
		"dob": "11/1/1983"
	},
	{
		"id": 254,
		"fname": "Annabela",
		"lname": "Scroyton",
		"email": "ascroyton71@issuu.com",
		"gender": "Non-binary",
		"phone": "515-431-2625",
		"dob": "12/29/2003"
	},
	{
		"id": 255,
		"fname": "Adele",
		"lname": "Cope",
		"email": "acope72@scribd.com",
		"gender": "Agender",
		"phone": "852-854-6438",
		"dob": "7/30/1974"
	},
	{
		"id": 256,
		"fname": "Lorianne",
		"lname": "Josupeit",
		"email": "ljosupeit73@nhs.uk",
		"gender": "Genderfluid",
		"phone": "721-246-9378",
		"dob": "2/5/1973"
	},
	{
		"id": 257,
		"fname": "Nial",
		"lname": "Pynn",
		"email": "npynn74@opera.com",
		"gender": "Agender",
		"phone": "829-371-9228",
		"dob": "2/5/2009"
	},
	{
		"id": 258,
		"fname": "Graham",
		"lname": "Gebb",
		"email": "ggebb75@cafepress.com",
		"gender": "Non-binary",
		"phone": "476-831-1586",
		"dob": "1/7/2009"
	},
	{
		"id": 259,
		"fname": "Titos",
		"lname": "Buckney",
		"email": "tbuckney76@microsoft.com",
		"gender": "Male",
		"phone": "464-883-7331",
		"dob": "2/10/1972"
	},
	{
		"id": 260,
		"fname": "Georgine",
		"lname": "Jerams",
		"email": "gjerams77@free.fr",
		"gender": "Bigender",
		"phone": "734-885-4561",
		"dob": "2/14/1980"
	},
	{
		"id": 261,
		"fname": "Claresta",
		"lname": "Hitzmann",
		"email": "chitzmann78@ow.ly",
		"gender": "Bigender",
		"phone": "238-814-5084",
		"dob": "11/29/2003"
	},
	{
		"id": 262,
		"fname": "Adela",
		"lname": "Byllam",
		"email": "abyllam79@statcounter.com",
		"gender": "Female",
		"phone": "824-902-4201",
		"dob": "6/18/2010"
	},
	{
		"id": 263,
		"fname": "Toddy",
		"lname": "Leither",
		"email": "tleither7a@about.com",
		"gender": "Non-binary",
		"phone": "693-583-3849",
		"dob": "2/28/1985"
	},
	{
		"id": 264,
		"fname": "Naomi",
		"lname": "Cloke",
		"email": "ncloke7b@cnet.com",
		"gender": "Bigender",
		"phone": "423-500-5637",
		"dob": "1/17/1994"
	},
	{
		"id": 265,
		"fname": "Torey",
		"lname": "Syde",
		"email": "tsyde7c@bloglovin.com",
		"gender": "Non-binary",
		"phone": "608-992-6079",
		"dob": "5/26/1972"
	},
	{
		"id": 266,
		"fname": "Enrique",
		"lname": "Whipp",
		"email": "ewhipp7d@spiegel.de",
		"gender": "Male",
		"phone": "567-840-9981",
		"dob": "2/5/1984"
	},
	{
		"id": 267,
		"fname": "Ginger",
		"lname": "Tukely",
		"email": "gtukely7e@sciencedaily.com",
		"gender": "Non-binary",
		"phone": "862-239-3356",
		"dob": "4/27/1991"
	},
	{
		"id": 268,
		"fname": "Micah",
		"lname": "McArdle",
		"email": "mmcardle7f@latimes.com",
		"gender": "Female",
		"phone": "758-365-4820",
		"dob": "1/27/1994"
	},
	{
		"id": 269,
		"fname": "Don",
		"lname": "Lammie",
		"email": "dlammie7g@stumbleupon.com",
		"gender": "Genderqueer",
		"phone": "610-488-2334",
		"dob": "8/14/1993"
	},
	{
		"id": 270,
		"fname": "Annabelle",
		"lname": "Peres",
		"email": "aperes7h@berkeley.edu",
		"gender": "Agender",
		"phone": "839-427-9869",
		"dob": "11/5/1983"
	},
	{
		"id": 271,
		"fname": "Neale",
		"lname": "Seamark",
		"email": "nseamark7i@gravatar.com",
		"gender": "Male",
		"phone": "440-572-8912",
		"dob": "12/27/2004"
	},
	{
		"id": 272,
		"fname": "Denys",
		"lname": "Bamborough",
		"email": "dbamborough7j@jigsy.com",
		"gender": "Bigender",
		"phone": "243-118-8430",
		"dob": "10/21/1980"
	},
	{
		"id": 273,
		"fname": "Lawton",
		"lname": "Bilbey",
		"email": "lbilbey7k@google.com",
		"gender": "Female",
		"phone": "450-232-4080",
		"dob": "3/23/1991"
	},
	{
		"id": 274,
		"fname": "Zolly",
		"lname": "Shevlan",
		"email": "zshevlan7l@w3.org",
		"gender": "Non-binary",
		"phone": "703-167-7224",
		"dob": "8/22/2009"
	},
	{
		"id": 275,
		"fname": "Jere",
		"lname": "Hoult",
		"email": "jhoult7m@goodreads.com",
		"gender": "Non-binary",
		"phone": "157-873-3137",
		"dob": "1/29/1975"
	},
	{
		"id": 276,
		"fname": "Marquita",
		"lname": "Harroway",
		"email": "mharroway7n@fc2.com",
		"gender": "Polygender",
		"phone": "159-755-5120",
		"dob": "9/2/1972"
	},
	{
		"id": 277,
		"fname": "Belita",
		"lname": "Ritmeyer",
		"email": "britmeyer7o@dailymotion.com",
		"gender": "Non-binary",
		"phone": "564-547-0179",
		"dob": "7/7/2010"
	},
	{
		"id": 278,
		"fname": "Vasilis",
		"lname": "Milbourne",
		"email": "vmilbourne7p@jigsy.com",
		"gender": "Genderqueer",
		"phone": "957-909-6754",
		"dob": "5/25/1975"
	},
	{
		"id": 279,
		"fname": "Lina",
		"lname": "Chapple",
		"email": "lchapple7q@mlb.com",
		"gender": "Agender",
		"phone": "678-231-2360",
		"dob": "3/22/1972"
	},
	{
		"id": 280,
		"fname": "Denna",
		"lname": "Medcraft",
		"email": "dmedcraft7r@google.com",
		"gender": "Genderqueer",
		"phone": "272-700-5217",
		"dob": "3/13/2008"
	},
	{
		"id": 281,
		"fname": "Ynes",
		"lname": "Smee",
		"email": "ysmee7s@un.org",
		"gender": "Agender",
		"phone": "662-593-0373",
		"dob": "4/21/1994"
	},
	{
		"id": 282,
		"fname": "Carly",
		"lname": "Comar",
		"email": "ccomar7t@miitbeian.gov.cn",
		"gender": "Agender",
		"phone": "808-396-0934",
		"dob": "8/2/2004"
	},
	{
		"id": 283,
		"fname": "Patton",
		"lname": "Le Noir",
		"email": "plenoir7u@nydailynews.com",
		"gender": "Female",
		"phone": "385-458-7812",
		"dob": "4/2/1972"
	},
	{
		"id": 284,
		"fname": "Griff",
		"lname": "McCosker",
		"email": "gmccosker7v@g.co",
		"gender": "Genderqueer",
		"phone": "945-449-8911",
		"dob": "1/19/1999"
	},
	{
		"id": 285,
		"fname": "Far",
		"lname": "O'Carran",
		"email": "focarran7w@w3.org",
		"gender": "Agender",
		"phone": "426-501-6903",
		"dob": "10/28/2001"
	},
	{
		"id": 286,
		"fname": "Valentia",
		"lname": "MacGaffey",
		"email": "vmacgaffey7x@tinyurl.com",
		"gender": "Female",
		"phone": "883-143-1744",
		"dob": "4/2/1978"
	},
	{
		"id": 287,
		"fname": "Angelita",
		"lname": "Strathdee",
		"email": "astrathdee7y@bloglovin.com",
		"gender": "Non-binary",
		"phone": "661-177-7139",
		"dob": "2/21/1975"
	},
	{
		"id": 288,
		"fname": "Emmet",
		"lname": "Jones",
		"email": "ejones7z@flickr.com",
		"gender": "Female",
		"phone": "950-578-4707",
		"dob": "10/12/1971"
	},
	{
		"id": 289,
		"fname": "Kale",
		"lname": "Shaplin",
		"email": "kshaplin80@cbsnews.com",
		"gender": "Polygender",
		"phone": "117-894-9704",
		"dob": "8/20/1979"
	},
	{
		"id": 290,
		"fname": "Alana",
		"lname": "Deeney",
		"email": "adeeney81@sitemeter.com",
		"gender": "Female",
		"phone": "732-329-9986",
		"dob": "1/9/2002"
	},
	{
		"id": 291,
		"fname": "Brynna",
		"lname": "Hele",
		"email": "bhele82@behance.net",
		"gender": "Genderqueer",
		"phone": "507-820-7261",
		"dob": "6/11/1985"
	},
	{
		"id": 292,
		"fname": "Janna",
		"lname": "Shenton",
		"email": "jshenton83@mayoclinic.com",
		"gender": "Agender",
		"phone": "400-662-5708",
		"dob": "4/22/1972"
	},
	{
		"id": 293,
		"fname": "Paulie",
		"lname": "Hamon",
		"email": "phamon84@devhub.com",
		"gender": "Non-binary",
		"phone": "210-518-8475",
		"dob": "8/1/1995"
	},
	{
		"id": 294,
		"fname": "Stillmann",
		"lname": "Cufflin",
		"email": "scufflin85@wordpress.org",
		"gender": "Genderfluid",
		"phone": "696-669-4347",
		"dob": "6/5/1992"
	},
	{
		"id": 295,
		"fname": "Sal",
		"lname": "Bartholomew",
		"email": "sbartholomew86@loc.gov",
		"gender": "Genderqueer",
		"phone": "823-510-9788",
		"dob": "10/29/1992"
	},
	{
		"id": 296,
		"fname": "Jenda",
		"lname": "Oliver",
		"email": "joliver87@gizmodo.com",
		"gender": "Genderqueer",
		"phone": "496-404-2149",
		"dob": "7/15/2008"
	},
	{
		"id": 297,
		"fname": "Jonie",
		"lname": "Aven",
		"email": "javen88@cpanel.net",
		"gender": "Polygender",
		"phone": "720-274-6946",
		"dob": "10/23/1991"
	},
	{
		"id": 298,
		"fname": "Denise",
		"lname": "Hearson",
		"email": "dhearson89@guardian.co.uk",
		"gender": "Non-binary",
		"phone": "893-762-3978",
		"dob": "3/6/1986"
	},
	{
		"id": 299,
		"fname": "Dexter",
		"lname": "Learman",
		"email": "dlearman8a@thetimes.co.uk",
		"gender": "Bigender",
		"phone": "161-238-0252",
		"dob": "6/23/2006"
	},
	{
		"id": 300,
		"fname": "Dilly",
		"lname": "Debenham",
		"email": "ddebenham8b@smugmug.com",
		"gender": "Male",
		"phone": "818-247-1323",
		"dob": "8/2/1972"
	},
	{
		"id": 301,
		"fname": "Thalia",
		"lname": "Temby",
		"email": "ttemby8c@plala.or.jp",
		"gender": "Agender",
		"phone": "322-268-4047",
		"dob": "2/24/2000"
	},
	{
		"id": 302,
		"fname": "Tuesday",
		"lname": "Fentem",
		"email": "tfentem8d@pinterest.com",
		"gender": "Female",
		"phone": "618-243-0057",
		"dob": "1/7/2008"
	},
	{
		"id": 303,
		"fname": "Melinda",
		"lname": "Brunon",
		"email": "mbrunon8e@examiner.com",
		"gender": "Female",
		"phone": "129-746-2898",
		"dob": "10/29/2001"
	},
	{
		"id": 304,
		"fname": "Melva",
		"lname": "Allonby",
		"email": "mallonby8f@psu.edu",
		"gender": "Polygender",
		"phone": "687-981-1006",
		"dob": "8/28/2002"
	},
	{
		"id": 305,
		"fname": "Burlie",
		"lname": "Attwoull",
		"email": "battwoull8g@sina.com.cn",
		"gender": "Female",
		"phone": "103-923-6862",
		"dob": "1/24/1978"
	},
	{
		"id": 306,
		"fname": "Haskel",
		"lname": "MacKaig",
		"email": "hmackaig8h@stanford.edu",
		"gender": "Agender",
		"phone": "597-602-2876",
		"dob": "4/30/1971"
	},
	{
		"id": 307,
		"fname": "Ginnifer",
		"lname": "Gierardi",
		"email": "ggierardi8i@ehow.com",
		"gender": "Genderqueer",
		"phone": "482-559-2617",
		"dob": "10/24/1998"
	},
	{
		"id": 308,
		"fname": "Lilian",
		"lname": "Stillwell",
		"email": "lstillwell8j@weebly.com",
		"gender": "Polygender",
		"phone": "634-620-2182",
		"dob": "3/26/2000"
	},
	{
		"id": 309,
		"fname": "Odelia",
		"lname": "Varey",
		"email": "ovarey8k@state.tx.us",
		"gender": "Bigender",
		"phone": "539-108-5012",
		"dob": "1/1/2000"
	},
	{
		"id": 310,
		"fname": "Jazmin",
		"lname": "Kyme",
		"email": "jkyme8l@sourceforge.net",
		"gender": "Female",
		"phone": "745-533-4498",
		"dob": "9/11/1977"
	},
	{
		"id": 311,
		"fname": "Dolly",
		"lname": "Kehoe",
		"email": "dkehoe8m@tripadvisor.com",
		"gender": "Genderfluid",
		"phone": "543-377-1453",
		"dob": "10/11/1980"
	},
	{
		"id": 312,
		"fname": "Frazer",
		"lname": "Kennerknecht",
		"email": "fkennerknecht8n@youtu.be",
		"gender": "Polygender",
		"phone": "694-806-9083",
		"dob": "8/10/2010"
	},
	{
		"id": 313,
		"fname": "Domeniga",
		"lname": "Labuschagne",
		"email": "dlabuschagne8o@jigsy.com",
		"gender": "Polygender",
		"phone": "192-397-3214",
		"dob": "5/23/1994"
	},
	{
		"id": 314,
		"fname": "Irina",
		"lname": "Reilinger",
		"email": "ireilinger8p@auda.org.au",
		"gender": "Genderqueer",
		"phone": "152-854-6227",
		"dob": "1/23/1972"
	},
	{
		"id": 315,
		"fname": "Ethelind",
		"lname": "Packe",
		"email": "epacke8q@digg.com",
		"gender": "Non-binary",
		"phone": "959-247-8300",
		"dob": "5/6/1982"
	},
	{
		"id": 316,
		"fname": "Ola",
		"lname": "Graalmans",
		"email": "ograalmans8r@dagondesign.com",
		"gender": "Female",
		"phone": "575-414-2000",
		"dob": "2/19/2000"
	},
	{
		"id": 317,
		"fname": "Dido",
		"lname": "Jiras",
		"email": "djiras8s@quantcast.com",
		"gender": "Non-binary",
		"phone": "223-286-3656",
		"dob": "10/19/1988"
	},
	{
		"id": 318,
		"fname": "Tammie",
		"lname": "Alabaster",
		"email": "talabaster8t@ucsd.edu",
		"gender": "Polygender",
		"phone": "279-783-4372",
		"dob": "5/18/1986"
	},
	{
		"id": 319,
		"fname": "Leroy",
		"lname": "Scranedge",
		"email": "lscranedge8u@comcast.net",
		"gender": "Bigender",
		"phone": "348-539-4207",
		"dob": "9/23/1993"
	},
	{
		"id": 320,
		"fname": "Dominique",
		"lname": "Joust",
		"email": "djoust8v@macromedia.com",
		"gender": "Genderfluid",
		"phone": "790-973-2235",
		"dob": "11/17/1977"
	},
	{
		"id": 321,
		"fname": "Bibbye",
		"lname": "Etchells",
		"email": "betchells8w@cnbc.com",
		"gender": "Polygender",
		"phone": "464-732-1255",
		"dob": "5/14/1972"
	},
	{
		"id": 322,
		"fname": "Caddric",
		"lname": "Hastie",
		"email": "chastie8x@opensource.org",
		"gender": "Polygender",
		"phone": "396-388-9667",
		"dob": "11/15/2005"
	},
	{
		"id": 323,
		"fname": "Vassily",
		"lname": "Aberdeen",
		"email": "vaberdeen8y@dyndns.org",
		"gender": "Female",
		"phone": "204-317-9330",
		"dob": "6/18/1971"
	},
	{
		"id": 324,
		"fname": "Sam",
		"lname": "Bliss",
		"email": "sbliss8z@phpbb.com",
		"gender": "Agender",
		"phone": "966-295-1639",
		"dob": "9/14/2005"
	},
	{
		"id": 325,
		"fname": "Jody",
		"lname": "Itzcak",
		"email": "jitzcak90@prnewswire.com",
		"gender": "Female",
		"phone": "803-821-8768",
		"dob": "6/25/2002"
	},
	{
		"id": 326,
		"fname": "Clay",
		"lname": "Tayspell",
		"email": "ctayspell91@booking.com",
		"gender": "Genderqueer",
		"phone": "384-136-4598",
		"dob": "1/15/1981"
	},
	{
		"id": 327,
		"fname": "Gamaliel",
		"lname": "Arrighetti",
		"email": "garrighetti92@mtv.com",
		"gender": "Male",
		"phone": "143-501-8647",
		"dob": "4/10/1975"
	},
	{
		"id": 328,
		"fname": "Starlene",
		"lname": "Jirek",
		"email": "sjirek93@last.fm",
		"gender": "Male",
		"phone": "411-660-0110",
		"dob": "9/10/2008"
	},
	{
		"id": 329,
		"fname": "Perri",
		"lname": "Lewcock",
		"email": "plewcock94@angelfire.com",
		"gender": "Genderfluid",
		"phone": "780-936-6344",
		"dob": "6/4/1982"
	},
	{
		"id": 330,
		"fname": "Rahal",
		"lname": "De Freyne",
		"email": "rdefreyne95@joomla.org",
		"gender": "Male",
		"phone": "425-752-2684",
		"dob": "11/24/1981"
	},
	{
		"id": 331,
		"fname": "Gardiner",
		"lname": "Stollenwerck",
		"email": "gstollenwerck96@wisc.edu",
		"gender": "Polygender",
		"phone": "944-771-2423",
		"dob": "9/1/1994"
	},
	{
		"id": 332,
		"fname": "Babette",
		"lname": "Stapylton",
		"email": "bstapylton97@unblog.fr",
		"gender": "Bigender",
		"phone": "763-451-7646",
		"dob": "8/13/1998"
	},
	{
		"id": 333,
		"fname": "Devin",
		"lname": "Dunbabin",
		"email": "ddunbabin98@wikipedia.org",
		"gender": "Non-binary",
		"phone": "315-437-9639",
		"dob": "8/16/1998"
	},
	{
		"id": 334,
		"fname": "Laurice",
		"lname": "Hastings",
		"email": "lhastings99@skype.com",
		"gender": "Bigender",
		"phone": "935-831-4421",
		"dob": "2/25/1980"
	},
	{
		"id": 335,
		"fname": "Aleen",
		"lname": "Izkovicz",
		"email": "aizkovicz9a@scientificamerican.com",
		"gender": "Genderfluid",
		"phone": "689-421-1581",
		"dob": "4/19/1991"
	},
	{
		"id": 336,
		"fname": "Adelaide",
		"lname": "Banting",
		"email": "abanting9b@redcross.org",
		"gender": "Male",
		"phone": "870-963-0029",
		"dob": "4/10/2002"
	},
	{
		"id": 337,
		"fname": "Tory",
		"lname": "McGeagh",
		"email": "tmcgeagh9c@feedburner.com",
		"gender": "Agender",
		"phone": "998-901-9862",
		"dob": "1/19/1985"
	},
	{
		"id": 338,
		"fname": "Berty",
		"lname": "Chamley",
		"email": "bchamley9d@kickstarter.com",
		"gender": "Agender",
		"phone": "897-779-5520",
		"dob": "12/11/1975"
	},
	{
		"id": 339,
		"fname": "Conway",
		"lname": "Warner",
		"email": "cwarner9e@smugmug.com",
		"gender": "Female",
		"phone": "633-744-4978",
		"dob": "1/10/1980"
	},
	{
		"id": 340,
		"fname": "Carlyle",
		"lname": "Becom",
		"email": "cbecom9f@tumblr.com",
		"gender": "Genderqueer",
		"phone": "561-309-0611",
		"dob": "4/9/1997"
	},
	{
		"id": 341,
		"fname": "Ewen",
		"lname": "Marsie",
		"email": "emarsie9g@pen.io",
		"gender": "Non-binary",
		"phone": "751-723-8954",
		"dob": "7/2/1988"
	},
	{
		"id": 342,
		"fname": "Melisent",
		"lname": "Penk",
		"email": "mpenk9h@mozilla.org",
		"gender": "Agender",
		"phone": "887-831-4724",
		"dob": "5/23/1983"
	},
	{
		"id": 343,
		"fname": "Wilmer",
		"lname": "MacMeekan",
		"email": "wmacmeekan9i@nytimes.com",
		"gender": "Bigender",
		"phone": "905-185-9182",
		"dob": "7/30/1995"
	},
	{
		"id": 344,
		"fname": "Leshia",
		"lname": "Ciccottio",
		"email": "lciccottio9j@naver.com",
		"gender": "Polygender",
		"phone": "195-879-7759",
		"dob": "7/14/1998"
	},
	{
		"id": 345,
		"fname": "Corrie",
		"lname": "Alyoshin",
		"email": "calyoshin9k@creativecommons.org",
		"gender": "Genderqueer",
		"phone": "999-263-4325",
		"dob": "6/28/1997"
	},
	{
		"id": 346,
		"fname": "Leora",
		"lname": "Klehyn",
		"email": "lklehyn9l@freewebs.com",
		"gender": "Genderqueer",
		"phone": "834-636-9932",
		"dob": "9/15/1982"
	},
	{
		"id": 347,
		"fname": "Carolan",
		"lname": "McLoney",
		"email": "cmcloney9m@addthis.com",
		"gender": "Agender",
		"phone": "180-153-1776",
		"dob": "2/15/1985"
	},
	{
		"id": 348,
		"fname": "Winthrop",
		"lname": "Rackham",
		"email": "wrackham9n@goo.ne.jp",
		"gender": "Non-binary",
		"phone": "778-759-1247",
		"dob": "5/18/2002"
	},
	{
		"id": 349,
		"fname": "Skyler",
		"lname": "Hamshere",
		"email": "shamshere9o@alexa.com",
		"gender": "Genderfluid",
		"phone": "297-324-1676",
		"dob": "2/12/2002"
	},
	{
		"id": 350,
		"fname": "Jens",
		"lname": "Milverton",
		"email": "jmilverton9p@lulu.com",
		"gender": "Genderqueer",
		"phone": "540-714-5192",
		"dob": "11/22/1983"
	},
	{
		"id": 351,
		"fname": "Alex",
		"lname": "Rozec",
		"email": "arozec9q@wunderground.com",
		"gender": "Genderfluid",
		"phone": "697-374-9689",
		"dob": "7/1/1997"
	},
	{
		"id": 352,
		"fname": "Cassie",
		"lname": "Kliemann",
		"email": "ckliemann9r@weibo.com",
		"gender": "Genderfluid",
		"phone": "266-624-5937",
		"dob": "2/21/1979"
	},
	{
		"id": 353,
		"fname": "Cicely",
		"lname": "Addams",
		"email": "caddams9s@google.co.jp",
		"gender": "Polygender",
		"phone": "851-412-9086",
		"dob": "3/13/1994"
	},
	{
		"id": 354,
		"fname": "Alyson",
		"lname": "Branchet",
		"email": "abranchet9t@dion.ne.jp",
		"gender": "Non-binary",
		"phone": "745-809-9339",
		"dob": "10/26/1992"
	},
	{
		"id": 355,
		"fname": "Raff",
		"lname": "Gabotti",
		"email": "rgabotti9u@tripadvisor.com",
		"gender": "Agender",
		"phone": "859-608-4689",
		"dob": "11/20/1973"
	},
	{
		"id": 356,
		"fname": "Jan",
		"lname": "Culpan",
		"email": "jculpan9v@odnoklassniki.ru",
		"gender": "Genderqueer",
		"phone": "200-709-7538",
		"dob": "2/15/1996"
	},
	{
		"id": 357,
		"fname": "Timmy",
		"lname": "Gremain",
		"email": "tgremain9w@patch.com",
		"gender": "Non-binary",
		"phone": "559-649-2696",
		"dob": "1/30/1975"
	},
	{
		"id": 358,
		"fname": "Min",
		"lname": "Axell",
		"email": "maxell9x@ucla.edu",
		"gender": "Male",
		"phone": "814-466-0096",
		"dob": "12/25/2001"
	},
	{
		"id": 359,
		"fname": "Pammie",
		"lname": "Cragg",
		"email": "pcragg9y@hp.com",
		"gender": "Male",
		"phone": "698-975-6995",
		"dob": "12/26/1982"
	},
	{
		"id": 360,
		"fname": "Xavier",
		"lname": "Kruschev",
		"email": "xkruschev9z@scientificamerican.com",
		"gender": "Agender",
		"phone": "416-209-3931",
		"dob": "6/10/2007"
	},
	{
		"id": 361,
		"fname": "Maire",
		"lname": "Sute",
		"email": "msutea0@flickr.com",
		"gender": "Female",
		"phone": "572-566-6486",
		"dob": "5/17/2008"
	},
	{
		"id": 362,
		"fname": "Noak",
		"lname": "Dyer",
		"email": "ndyera1@yale.edu",
		"gender": "Genderqueer",
		"phone": "652-386-9156",
		"dob": "3/24/1972"
	},
	{
		"id": 363,
		"fname": "Gabie",
		"lname": "Enos",
		"email": "genosa2@webnode.com",
		"gender": "Bigender",
		"phone": "771-178-4436",
		"dob": "10/9/2010"
	},
	{
		"id": 364,
		"fname": "Angelina",
		"lname": "Sell",
		"email": "asella3@usgs.gov",
		"gender": "Agender",
		"phone": "804-172-8953",
		"dob": "10/4/2001"
	},
	{
		"id": 365,
		"fname": "Tallia",
		"lname": "O' Hern",
		"email": "toherna4@sciencedaily.com",
		"gender": "Genderfluid",
		"phone": "865-744-8618",
		"dob": "11/24/1986"
	},
	{
		"id": 366,
		"fname": "Silvester",
		"lname": "Ibbett",
		"email": "sibbetta5@nytimes.com",
		"gender": "Male",
		"phone": "832-743-0206",
		"dob": "5/5/1989"
	},
	{
		"id": 367,
		"fname": "Roselin",
		"lname": "Pietranek",
		"email": "rpietraneka6@e-recht24.de",
		"gender": "Genderfluid",
		"phone": "329-303-5764",
		"dob": "5/2/1993"
	},
	{
		"id": 368,
		"fname": "Charline",
		"lname": "Tuckey",
		"email": "ctuckeya7@ca.gov",
		"gender": "Bigender",
		"phone": "464-351-5646",
		"dob": "7/12/1992"
	},
	{
		"id": 369,
		"fname": "Debora",
		"lname": "Frangello",
		"email": "dfrangelloa8@mtv.com",
		"gender": "Non-binary",
		"phone": "448-422-7148",
		"dob": "3/17/2000"
	},
	{
		"id": 370,
		"fname": "Karalee",
		"lname": "Spittles",
		"email": "kspittlesa9@salon.com",
		"gender": "Female",
		"phone": "783-275-3422",
		"dob": "12/11/2004"
	},
	{
		"id": 371,
		"fname": "Bo",
		"lname": "Gartsyde",
		"email": "bgartsydeaa@livejournal.com",
		"gender": "Polygender",
		"phone": "132-217-9062",
		"dob": "3/27/2007"
	},
	{
		"id": 372,
		"fname": "Jacquie",
		"lname": "McGaugie",
		"email": "jmcgaugieab@uiuc.edu",
		"gender": "Male",
		"phone": "650-375-6673",
		"dob": "2/25/2001"
	},
	{
		"id": 373,
		"fname": "Bevan",
		"lname": "Nesbit",
		"email": "bnesbitac@feedburner.com",
		"gender": "Non-binary",
		"phone": "424-631-6967",
		"dob": "4/7/1979"
	},
	{
		"id": 374,
		"fname": "Burch",
		"lname": "Aronowitz",
		"email": "baronowitzad@booking.com",
		"gender": "Bigender",
		"phone": "250-798-6283",
		"dob": "2/11/2007"
	},
	{
		"id": 375,
		"fname": "Dasie",
		"lname": "Moody",
		"email": "dmoodyae@discuz.net",
		"gender": "Genderqueer",
		"phone": "272-604-8739",
		"dob": "9/24/1981"
	},
	{
		"id": 376,
		"fname": "Curr",
		"lname": "Skehens",
		"email": "cskehensaf@miitbeian.gov.cn",
		"gender": "Agender",
		"phone": "238-607-3853",
		"dob": "3/15/2005"
	},
	{
		"id": 377,
		"fname": "Laurel",
		"lname": "Grigs",
		"email": "lgrigsag@illinois.edu",
		"gender": "Genderfluid",
		"phone": "668-793-1941",
		"dob": "12/25/2004"
	},
	{
		"id": 378,
		"fname": "Eolande",
		"lname": "Boater",
		"email": "eboaterah@bloglines.com",
		"gender": "Non-binary",
		"phone": "655-821-9346",
		"dob": "10/8/1983"
	},
	{
		"id": 379,
		"fname": "Alejoa",
		"lname": "Clerc",
		"email": "aclercai@163.com",
		"gender": "Agender",
		"phone": "623-182-6800",
		"dob": "6/3/2007"
	},
	{
		"id": 380,
		"fname": "Aime",
		"lname": "Culpen",
		"email": "aculpenaj@1688.com",
		"gender": "Polygender",
		"phone": "362-998-2580",
		"dob": "2/10/2003"
	},
	{
		"id": 381,
		"fname": "Gale",
		"lname": "Scotchmoor",
		"email": "gscotchmoorak@techcrunch.com",
		"gender": "Male",
		"phone": "948-302-7428",
		"dob": "7/20/2002"
	},
	{
		"id": 382,
		"fname": "Barclay",
		"lname": "Theunissen",
		"email": "btheunissenal@live.com",
		"gender": "Non-binary",
		"phone": "659-711-7218",
		"dob": "7/4/1990"
	},
	{
		"id": 383,
		"fname": "Verne",
		"lname": "McGilvary",
		"email": "vmcgilvaryam@tmall.com",
		"gender": "Female",
		"phone": "542-399-2127",
		"dob": "7/25/1974"
	},
	{
		"id": 384,
		"fname": "Patric",
		"lname": "Frew",
		"email": "pfrewan@yellowbook.com",
		"gender": "Female",
		"phone": "884-798-1907",
		"dob": "7/23/2001"
	},
	{
		"id": 385,
		"fname": "Chrysler",
		"lname": "Beevor",
		"email": "cbeevorao@nsw.gov.au",
		"gender": "Non-binary",
		"phone": "262-246-1184",
		"dob": "7/25/1992"
	},
	{
		"id": 386,
		"fname": "Tawsha",
		"lname": "Rusted",
		"email": "trustedap@lulu.com",
		"gender": "Female",
		"phone": "525-529-1170",
		"dob": "10/18/1995"
	},
	{
		"id": 387,
		"fname": "Ewan",
		"lname": "Dodworth",
		"email": "edodworthaq@indiegogo.com",
		"gender": "Polygender",
		"phone": "154-349-8549",
		"dob": "2/26/1995"
	},
	{
		"id": 388,
		"fname": "Cinderella",
		"lname": "Dally",
		"email": "cdallyar@moonfruit.com",
		"gender": "Polygender",
		"phone": "492-836-0955",
		"dob": "10/1/1982"
	},
	{
		"id": 389,
		"fname": "Allie",
		"lname": "Janny",
		"email": "ajannyas@nasa.gov",
		"gender": "Polygender",
		"phone": "689-832-4282",
		"dob": "10/22/1975"
	},
	{
		"id": 390,
		"fname": "Edmon",
		"lname": "Gooley",
		"email": "egooleyat@google.pl",
		"gender": "Genderqueer",
		"phone": "267-660-6973",
		"dob": "9/2/1983"
	},
	{
		"id": 391,
		"fname": "Brew",
		"lname": "Frunks",
		"email": "bfrunksau@topsy.com",
		"gender": "Male",
		"phone": "596-699-0635",
		"dob": "12/17/2007"
	},
	{
		"id": 392,
		"fname": "Shellysheldon",
		"lname": "Gooderridge",
		"email": "sgooderridgeav@springer.com",
		"gender": "Non-binary",
		"phone": "676-296-4611",
		"dob": "7/17/1980"
	},
	{
		"id": 393,
		"fname": "Arther",
		"lname": "Carlisi",
		"email": "acarlisiaw@ucoz.com",
		"gender": "Genderfluid",
		"phone": "708-922-2427",
		"dob": "7/15/1971"
	},
	{
		"id": 394,
		"fname": "Curtice",
		"lname": "Placide",
		"email": "cplacideax@ask.com",
		"gender": "Genderfluid",
		"phone": "168-943-5609",
		"dob": "10/9/2000"
	},
	{
		"id": 395,
		"fname": "Joelie",
		"lname": "Willox",
		"email": "jwilloxay@amazon.co.jp",
		"gender": "Genderqueer",
		"phone": "886-358-3275",
		"dob": "8/8/2008"
	},
	{
		"id": 396,
		"fname": "Mallissa",
		"lname": "Toffalo",
		"email": "mtoffaloaz@jimdo.com",
		"gender": "Female",
		"phone": "318-394-0628",
		"dob": "4/23/2006"
	},
	{
		"id": 397,
		"fname": "Mallory",
		"lname": "Everix",
		"email": "meverixb0@etsy.com",
		"gender": "Polygender",
		"phone": "702-998-0678",
		"dob": "2/15/2007"
	},
	{
		"id": 398,
		"fname": "Kendall",
		"lname": "Edmundson",
		"email": "kedmundsonb1@apache.org",
		"gender": "Agender",
		"phone": "165-847-8093",
		"dob": "6/17/1992"
	},
	{
		"id": 399,
		"fname": "Maribeth",
		"lname": "Ertel",
		"email": "mertelb2@japanpost.jp",
		"gender": "Bigender",
		"phone": "268-417-3641",
		"dob": "9/12/1987"
	},
	{
		"id": 400,
		"fname": "Catlin",
		"lname": "Woollard",
		"email": "cwoollardb3@tmall.com",
		"gender": "Male",
		"phone": "558-584-9106",
		"dob": "9/2/1996"
	},
	{
		"id": 401,
		"fname": "Lorilyn",
		"lname": "Filkin",
		"email": "lfilkinb4@geocities.com",
		"gender": "Bigender",
		"phone": "249-768-7294",
		"dob": "3/18/1984"
	},
	{
		"id": 402,
		"fname": "Gun",
		"lname": "Toohey",
		"email": "gtooheyb5@is.gd",
		"gender": "Agender",
		"phone": "404-945-7342",
		"dob": "9/12/1981"
	},
	{
		"id": 403,
		"fname": "Selene",
		"lname": "Uttermare",
		"email": "suttermareb6@live.com",
		"gender": "Non-binary",
		"phone": "623-980-1894",
		"dob": "6/13/1982"
	},
	{
		"id": 404,
		"fname": "Jonis",
		"lname": "Bagnal",
		"email": "jbagnalb7@clickbank.net",
		"gender": "Genderqueer",
		"phone": "768-243-9070",
		"dob": "8/1/1974"
	},
	{
		"id": 405,
		"fname": "Clarisse",
		"lname": "Quarterman",
		"email": "cquartermanb8@sciencedirect.com",
		"gender": "Polygender",
		"phone": "574-467-8140",
		"dob": "8/20/1978"
	},
	{
		"id": 406,
		"fname": "Gregg",
		"lname": "Youle",
		"email": "gyouleb9@usatoday.com",
		"gender": "Genderqueer",
		"phone": "814-572-8374",
		"dob": "10/26/2003"
	},
	{
		"id": 407,
		"fname": "Bryn",
		"lname": "Frisel",
		"email": "bfriselba@multiply.com",
		"gender": "Polygender",
		"phone": "413-594-1542",
		"dob": "11/12/2007"
	},
	{
		"id": 408,
		"fname": "Pattie",
		"lname": "Honisch",
		"email": "phonischbb@i2i.jp",
		"gender": "Genderqueer",
		"phone": "123-575-7882",
		"dob": "7/5/2009"
	},
	{
		"id": 409,
		"fname": "Colman",
		"lname": "Mount",
		"email": "cmountbc@wunderground.com",
		"gender": "Genderqueer",
		"phone": "710-776-9721",
		"dob": "1/27/1998"
	},
	{
		"id": 410,
		"fname": "Andee",
		"lname": "Armitage",
		"email": "aarmitagebd@google.com.br",
		"gender": "Female",
		"phone": "548-980-6269",
		"dob": "6/5/1976"
	},
	{
		"id": 411,
		"fname": "Estelle",
		"lname": "Durnell",
		"email": "edurnellbe@scribd.com",
		"gender": "Male",
		"phone": "504-493-4008",
		"dob": "6/11/1988"
	},
	{
		"id": 412,
		"fname": "Olly",
		"lname": "Ties",
		"email": "otiesbf@linkedin.com",
		"gender": "Agender",
		"phone": "186-655-6321",
		"dob": "8/16/2001"
	},
	{
		"id": 413,
		"fname": "Worden",
		"lname": "Stogill",
		"email": "wstogillbg@europa.eu",
		"gender": "Polygender",
		"phone": "703-900-8891",
		"dob": "10/1/1984"
	},
	{
		"id": 414,
		"fname": "Dyanna",
		"lname": "Ambrogelli",
		"email": "dambrogellibh@psu.edu",
		"gender": "Female",
		"phone": "258-280-5771",
		"dob": "2/22/2007"
	},
	{
		"id": 415,
		"fname": "Augustine",
		"lname": "Dahill",
		"email": "adahillbi@theguardian.com",
		"gender": "Male",
		"phone": "246-119-3853",
		"dob": "9/29/1987"
	},
	{
		"id": 416,
		"fname": "Kayle",
		"lname": "Abriani",
		"email": "kabrianibj@vk.com",
		"gender": "Female",
		"phone": "365-590-4590",
		"dob": "5/18/1979"
	},
	{
		"id": 417,
		"fname": "Rex",
		"lname": "Poad",
		"email": "rpoadbk@wunderground.com",
		"gender": "Agender",
		"phone": "492-753-6287",
		"dob": "9/3/1972"
	},
	{
		"id": 418,
		"fname": "Lea",
		"lname": "Puddin",
		"email": "lpuddinbl@gizmodo.com",
		"gender": "Genderfluid",
		"phone": "619-540-1756",
		"dob": "2/8/1977"
	},
	{
		"id": 419,
		"fname": "Cora",
		"lname": "Fetherby",
		"email": "cfetherbybm@nymag.com",
		"gender": "Female",
		"phone": "223-850-2554",
		"dob": "7/29/1993"
	},
	{
		"id": 420,
		"fname": "Damien",
		"lname": "Aujean",
		"email": "daujeanbn@arstechnica.com",
		"gender": "Female",
		"phone": "890-183-0090",
		"dob": "8/11/1975"
	},
	{
		"id": 421,
		"fname": "Darla",
		"lname": "Bratley",
		"email": "dbratleybo@diigo.com",
		"gender": "Genderfluid",
		"phone": "755-602-9376",
		"dob": "2/9/2003"
	},
	{
		"id": 422,
		"fname": "Kermie",
		"lname": "Reaveley",
		"email": "kreaveleybp@weebly.com",
		"gender": "Male",
		"phone": "521-721-1234",
		"dob": "4/29/1972"
	},
	{
		"id": 423,
		"fname": "Lita",
		"lname": "Paul",
		"email": "lpaulbq@opera.com",
		"gender": "Agender",
		"phone": "368-862-5426",
		"dob": "1/25/1982"
	},
	{
		"id": 424,
		"fname": "Darnell",
		"lname": "Blowing",
		"email": "dblowingbr@chron.com",
		"gender": "Genderfluid",
		"phone": "116-909-2188",
		"dob": "7/23/1985"
	},
	{
		"id": 425,
		"fname": "Tawnya",
		"lname": "Vasilechko",
		"email": "tvasilechkobs@i2i.jp",
		"gender": "Genderqueer",
		"phone": "697-603-6310",
		"dob": "4/24/1997"
	},
	{
		"id": 426,
		"fname": "Laurice",
		"lname": "Carlill",
		"email": "lcarlillbt@indiatimes.com",
		"gender": "Female",
		"phone": "200-304-6127",
		"dob": "6/6/2005"
	},
	{
		"id": 427,
		"fname": "Cyndy",
		"lname": "Pointing",
		"email": "cpointingbu@gov.uk",
		"gender": "Agender",
		"phone": "128-170-6414",
		"dob": "3/28/2000"
	},
	{
		"id": 428,
		"fname": "Cecilio",
		"lname": "Luxmoore",
		"email": "cluxmoorebv@dmoz.org",
		"gender": "Female",
		"phone": "133-541-2008",
		"dob": "8/31/1983"
	},
	{
		"id": 429,
		"fname": "Edi",
		"lname": "Carbett",
		"email": "ecarbettbw@wordpress.com",
		"gender": "Genderqueer",
		"phone": "300-322-3336",
		"dob": "1/14/1976"
	},
	{
		"id": 430,
		"fname": "Laurene",
		"lname": "Naisbet",
		"email": "lnaisbetbx@artisteer.com",
		"gender": "Agender",
		"phone": "612-898-5584",
		"dob": "3/9/2009"
	},
	{
		"id": 431,
		"fname": "Elna",
		"lname": "Armes",
		"email": "earmesby@youtu.be",
		"gender": "Agender",
		"phone": "613-177-3886",
		"dob": "4/16/1978"
	},
	{
		"id": 432,
		"fname": "Jelene",
		"lname": "O'Fogerty",
		"email": "jofogertybz@newsvine.com",
		"gender": "Polygender",
		"phone": "477-533-9762",
		"dob": "7/2/1975"
	},
	{
		"id": 433,
		"fname": "Leodora",
		"lname": "Dickings",
		"email": "ldickingsc0@arstechnica.com",
		"gender": "Non-binary",
		"phone": "908-856-8290",
		"dob": "9/17/1975"
	},
	{
		"id": 434,
		"fname": "Dottie",
		"lname": "Isacoff",
		"email": "disacoffc1@cbc.ca",
		"gender": "Bigender",
		"phone": "648-240-4083",
		"dob": "6/19/2003"
	},
	{
		"id": 435,
		"fname": "Rae",
		"lname": "Ferandez",
		"email": "rferandezc2@tuttocitta.it",
		"gender": "Female",
		"phone": "209-564-5292",
		"dob": "10/31/1973"
	},
	{
		"id": 436,
		"fname": "Stevie",
		"lname": "Ortell",
		"email": "sortellc3@facebook.com",
		"gender": "Genderfluid",
		"phone": "315-244-6483",
		"dob": "3/28/1997"
	},
	{
		"id": 437,
		"fname": "Demetri",
		"lname": "Mc Queen",
		"email": "dmcqueenc4@latimes.com",
		"gender": "Female",
		"phone": "704-284-1894",
		"dob": "8/5/2002"
	},
	{
		"id": 438,
		"fname": "Shea",
		"lname": "Abelson",
		"email": "sabelsonc5@spiegel.de",
		"gender": "Genderqueer",
		"phone": "412-410-7025",
		"dob": "5/8/1978"
	},
	{
		"id": 439,
		"fname": "Morgan",
		"lname": "Kimmitt",
		"email": "mkimmittc6@pbs.org",
		"gender": "Agender",
		"phone": "320-410-1591",
		"dob": "12/15/1979"
	},
	{
		"id": 440,
		"fname": "Garik",
		"lname": "Escala",
		"email": "gescalac7@paypal.com",
		"gender": "Polygender",
		"phone": "744-796-1486",
		"dob": "12/21/1984"
	},
	{
		"id": 441,
		"fname": "Paolo",
		"lname": "Cornfoot",
		"email": "pcornfootc8@canalblog.com",
		"gender": "Male",
		"phone": "695-814-9466",
		"dob": "12/25/2006"
	},
	{
		"id": 442,
		"fname": "Gale",
		"lname": "Adlem",
		"email": "gadlemc9@ft.com",
		"gender": "Agender",
		"phone": "600-215-5149",
		"dob": "11/10/2005"
	},
	{
		"id": 443,
		"fname": "Sela",
		"lname": "Carryer",
		"email": "scarryerca@economist.com",
		"gender": "Bigender",
		"phone": "325-766-9532",
		"dob": "8/19/1992"
	},
	{
		"id": 444,
		"fname": "Mathilda",
		"lname": "Nelsey",
		"email": "mnelseycb@epa.gov",
		"gender": "Genderfluid",
		"phone": "102-431-3994",
		"dob": "2/18/2007"
	},
	{
		"id": 445,
		"fname": "Lisetta",
		"lname": "O'Leary",
		"email": "lolearycc@wikipedia.org",
		"gender": "Agender",
		"phone": "589-708-1516",
		"dob": "8/13/1987"
	},
	{
		"id": 446,
		"fname": "Sydney",
		"lname": "Alvarado",
		"email": "salvaradocd@sphinn.com",
		"gender": "Genderfluid",
		"phone": "173-102-1816",
		"dob": "11/10/1979"
	},
	{
		"id": 447,
		"fname": "Israel",
		"lname": "Schust",
		"email": "ischustce@webmd.com",
		"gender": "Genderfluid",
		"phone": "707-319-1739",
		"dob": "8/9/2001"
	},
	{
		"id": 448,
		"fname": "Gabie",
		"lname": "McColley",
		"email": "gmccolleycf@printfriendly.com",
		"gender": "Agender",
		"phone": "795-976-4663",
		"dob": "2/25/1976"
	},
	{
		"id": 449,
		"fname": "Ramon",
		"lname": "Midson",
		"email": "rmidsoncg@cbc.ca",
		"gender": "Genderfluid",
		"phone": "863-652-2897",
		"dob": "8/22/1992"
	},
	{
		"id": 450,
		"fname": "Codee",
		"lname": "Markos",
		"email": "cmarkosch@prnewswire.com",
		"gender": "Female",
		"phone": "595-440-6304",
		"dob": "9/26/1978"
	},
	{
		"id": 451,
		"fname": "Kelly",
		"lname": "Lobbe",
		"email": "klobbeci@yolasite.com",
		"gender": "Polygender",
		"phone": "509-764-0322",
		"dob": "11/25/2008"
	},
	{
		"id": 452,
		"fname": "Rodrique",
		"lname": "Prescot",
		"email": "rprescotcj@unblog.fr",
		"gender": "Genderqueer",
		"phone": "784-864-8965",
		"dob": "9/26/1995"
	},
	{
		"id": 453,
		"fname": "Petronille",
		"lname": "Gonthard",
		"email": "pgonthardck@cpanel.net",
		"gender": "Non-binary",
		"phone": "427-217-2974",
		"dob": "3/1/1994"
	},
	{
		"id": 454,
		"fname": "Ali",
		"lname": "Pitfield",
		"email": "apitfieldcl@list-manage.com",
		"gender": "Female",
		"phone": "858-962-3889",
		"dob": "8/20/1973"
	},
	{
		"id": 455,
		"fname": "Susi",
		"lname": "Breckin",
		"email": "sbreckincm@intel.com",
		"gender": "Non-binary",
		"phone": "322-650-9277",
		"dob": "12/7/1996"
	},
	{
		"id": 456,
		"fname": "Faith",
		"lname": "Murcutt",
		"email": "fmurcuttcn@tinypic.com",
		"gender": "Polygender",
		"phone": "797-754-3733",
		"dob": "9/17/2004"
	},
	{
		"id": 457,
		"fname": "Sal",
		"lname": "Woolfitt",
		"email": "swoolfittco@360.cn",
		"gender": "Agender",
		"phone": "972-973-1530",
		"dob": "5/22/2007"
	},
	{
		"id": 458,
		"fname": "Melamie",
		"lname": "Bleyman",
		"email": "mbleymancp@studiopress.com",
		"gender": "Male",
		"phone": "593-151-3319",
		"dob": "10/12/1973"
	},
	{
		"id": 459,
		"fname": "Karena",
		"lname": "Coy",
		"email": "kcoycq@tiny.cc",
		"gender": "Genderfluid",
		"phone": "950-981-0491",
		"dob": "11/16/1979"
	},
	{
		"id": 460,
		"fname": "Roy",
		"lname": "Mattschas",
		"email": "rmattschascr@amazonaws.com",
		"gender": "Bigender",
		"phone": "705-597-9896",
		"dob": "9/25/2009"
	},
	{
		"id": 461,
		"fname": "Wit",
		"lname": "Persicke",
		"email": "wpersickecs@yale.edu",
		"gender": "Agender",
		"phone": "139-322-7631",
		"dob": "8/28/2000"
	},
	{
		"id": 462,
		"fname": "Wrennie",
		"lname": "Downing",
		"email": "wdowningct@prnewswire.com",
		"gender": "Non-binary",
		"phone": "580-834-8534",
		"dob": "5/18/2007"
	},
	{
		"id": 463,
		"fname": "Luella",
		"lname": "Cunrado",
		"email": "lcunradocu@wordpress.org",
		"gender": "Non-binary",
		"phone": "814-719-8965",
		"dob": "12/30/1981"
	},
	{
		"id": 464,
		"fname": "Donaugh",
		"lname": "Alaway",
		"email": "dalawaycv@booking.com",
		"gender": "Genderqueer",
		"phone": "494-392-0180",
		"dob": "10/12/1982"
	},
	{
		"id": 465,
		"fname": "Rivi",
		"lname": "Feld",
		"email": "rfeldcw@jimdo.com",
		"gender": "Agender",
		"phone": "594-297-6534",
		"dob": "1/11/2001"
	},
	{
		"id": 466,
		"fname": "Oneida",
		"lname": "Birk",
		"email": "obirkcx@wiley.com",
		"gender": "Female",
		"phone": "508-851-0860",
		"dob": "2/8/1990"
	},
	{
		"id": 467,
		"fname": "Sammy",
		"lname": "Newborn",
		"email": "snewborncy@census.gov",
		"gender": "Genderfluid",
		"phone": "565-163-0016",
		"dob": "4/23/2004"
	},
	{
		"id": 468,
		"fname": "Meier",
		"lname": "Fontel",
		"email": "mfontelcz@china.com.cn",
		"gender": "Polygender",
		"phone": "972-423-0795",
		"dob": "2/13/2000"
	},
	{
		"id": 469,
		"fname": "Benni",
		"lname": "Peris",
		"email": "bperisd0@chicagotribune.com",
		"gender": "Bigender",
		"phone": "606-730-5908",
		"dob": "9/23/1976"
	},
	{
		"id": 470,
		"fname": "Danielle",
		"lname": "Barabisch",
		"email": "dbarabischd1@accuweather.com",
		"gender": "Male",
		"phone": "905-862-1589",
		"dob": "1/11/1992"
	},
	{
		"id": 471,
		"fname": "Kettie",
		"lname": "Rawcliffe",
		"email": "krawcliffed2@craigslist.org",
		"gender": "Non-binary",
		"phone": "427-113-9108",
		"dob": "11/4/1970"
	},
	{
		"id": 472,
		"fname": "Haleigh",
		"lname": "Petyanin",
		"email": "hpetyanind3@telegraph.co.uk",
		"gender": "Bigender",
		"phone": "885-374-0439",
		"dob": "8/4/1980"
	},
	{
		"id": 473,
		"fname": "Ruttger",
		"lname": "Hudspith",
		"email": "rhudspithd4@discovery.com",
		"gender": "Agender",
		"phone": "957-683-2100",
		"dob": "2/27/2003"
	},
	{
		"id": 474,
		"fname": "Gertrud",
		"lname": "Tedorenko",
		"email": "gtedorenkod5@amazon.co.jp",
		"gender": "Male",
		"phone": "976-553-5775",
		"dob": "9/25/2002"
	},
	{
		"id": 475,
		"fname": "Patti",
		"lname": "Kemme",
		"email": "pkemmed6@msu.edu",
		"gender": "Male",
		"phone": "902-458-3862",
		"dob": "4/7/1997"
	},
	{
		"id": 476,
		"fname": "Lynnea",
		"lname": "Pendrill",
		"email": "lpendrilld7@si.edu",
		"gender": "Polygender",
		"phone": "337-562-2458",
		"dob": "4/29/1984"
	},
	{
		"id": 477,
		"fname": "Harmon",
		"lname": "Simons",
		"email": "hsimonsd8@reference.com",
		"gender": "Genderqueer",
		"phone": "339-279-7663",
		"dob": "9/29/2010"
	},
	{
		"id": 478,
		"fname": "Etty",
		"lname": "Jakuszewski",
		"email": "ejakuszewskid9@homestead.com",
		"gender": "Genderfluid",
		"phone": "105-830-2684",
		"dob": "2/1/1973"
	},
	{
		"id": 479,
		"fname": "Hillary",
		"lname": "Roze",
		"email": "hrozeda@ftc.gov",
		"gender": "Genderfluid",
		"phone": "963-121-4015",
		"dob": "10/21/2008"
	},
	{
		"id": 480,
		"fname": "Niccolo",
		"lname": "Haysom",
		"email": "nhaysomdb@booking.com",
		"gender": "Agender",
		"phone": "171-480-4202",
		"dob": "3/15/1993"
	},
	{
		"id": 481,
		"fname": "Leupold",
		"lname": "Ubank",
		"email": "lubankdc@about.me",
		"gender": "Genderqueer",
		"phone": "498-544-8688",
		"dob": "7/29/2000"
	},
	{
		"id": 482,
		"fname": "Vasilis",
		"lname": "Danskine",
		"email": "vdanskinedd@craigslist.org",
		"gender": "Male",
		"phone": "617-379-0623",
		"dob": "6/11/2004"
	},
	{
		"id": 483,
		"fname": "Allan",
		"lname": "Francombe",
		"email": "afrancombede@zimbio.com",
		"gender": "Genderfluid",
		"phone": "296-393-5254",
		"dob": "1/7/1989"
	},
	{
		"id": 484,
		"fname": "Aubree",
		"lname": "Dodson",
		"email": "adodsondf@opensource.org",
		"gender": "Genderfluid",
		"phone": "562-418-4347",
		"dob": "5/12/1974"
	},
	{
		"id": 485,
		"fname": "Winslow",
		"lname": "Southern",
		"email": "wsoutherndg@umn.edu",
		"gender": "Genderqueer",
		"phone": "949-562-4321",
		"dob": "12/2/1995"
	},
	{
		"id": 486,
		"fname": "Eduard",
		"lname": "Gooms",
		"email": "egoomsdh@soup.io",
		"gender": "Genderfluid",
		"phone": "801-290-1780",
		"dob": "9/15/1981"
	},
	{
		"id": 487,
		"fname": "Ricki",
		"lname": "Brockie",
		"email": "rbrockiedi@infoseek.co.jp",
		"gender": "Agender",
		"phone": "680-763-0766",
		"dob": "1/24/1999"
	},
	{
		"id": 488,
		"fname": "Ann-marie",
		"lname": "Bortolotti",
		"email": "abortolottidj@stanford.edu",
		"gender": "Male",
		"phone": "820-329-1144",
		"dob": "11/26/1992"
	},
	{
		"id": 489,
		"fname": "Sayres",
		"lname": "Rounsivall",
		"email": "srounsivalldk@yahoo.com",
		"gender": "Bigender",
		"phone": "756-153-1383",
		"dob": "4/19/2009"
	},
	{
		"id": 490,
		"fname": "Maje",
		"lname": "Lydon",
		"email": "mlydondl@printfriendly.com",
		"gender": "Female",
		"phone": "624-668-3850",
		"dob": "3/21/1971"
	},
	{
		"id": 491,
		"fname": "Hubert",
		"lname": "Brookes",
		"email": "hbrookesdm@list-manage.com",
		"gender": "Bigender",
		"phone": "283-738-6620",
		"dob": "12/17/1998"
	},
	{
		"id": 492,
		"fname": "George",
		"lname": "Aulsford",
		"email": "gaulsforddn@blogs.com",
		"gender": "Bigender",
		"phone": "208-649-1632",
		"dob": "6/26/1988"
	},
	{
		"id": 493,
		"fname": "Dell",
		"lname": "Esh",
		"email": "deshdo@boston.com",
		"gender": "Genderqueer",
		"phone": "164-663-4707",
		"dob": "1/3/1972"
	},
	{
		"id": 494,
		"fname": "Claude",
		"lname": "Kemster",
		"email": "ckemsterdp@icio.us",
		"gender": "Non-binary",
		"phone": "440-980-1493",
		"dob": "4/16/1978"
	},
	{
		"id": 495,
		"fname": "Cookie",
		"lname": "Haywood",
		"email": "chaywooddq@psu.edu",
		"gender": "Genderfluid",
		"phone": "728-628-5426",
		"dob": "1/19/1997"
	},
	{
		"id": 496,
		"fname": "Ruthy",
		"lname": "Clausen",
		"email": "rclausendr@blog.com",
		"gender": "Polygender",
		"phone": "881-303-5270",
		"dob": "10/13/1998"
	},
	{
		"id": 497,
		"fname": "Damaris",
		"lname": "Skellon",
		"email": "dskellonds@mail.ru",
		"gender": "Polygender",
		"phone": "323-252-4193",
		"dob": "1/15/1976"
	},
	{
		"id": 498,
		"fname": "Audy",
		"lname": "Duckworth",
		"email": "aduckworthdt@usda.gov",
		"gender": "Polygender",
		"phone": "317-101-9355",
		"dob": "7/14/1994"
	},
	{
		"id": 499,
		"fname": "Goldina",
		"lname": "Mateos",
		"email": "gmateosdu@google.ru",
		"gender": "Non-binary",
		"phone": "555-388-5345",
		"dob": "11/21/1974"
	},
	{
		"id": 500,
		"fname": "Hephzibah",
		"lname": "Vasilmanov",
		"email": "hvasilmanovdv@tiny.cc",
		"gender": "Bigender",
		"phone": "146-324-5900",
		"dob": "9/16/1983"
	}
]
